{"columns":[{"id":0,"name":"Base year"},{"id":32,"name":"1990"},{"id":33,"name":"1991"},{"id":34,"name":"1992"},{"id":35,"name":"1993"},{"id":36,"name":"1994"},{"id":37,"name":"1995"},{"id":38,"name":"1996"},{"id":39,"name":"1997"},{"id":40,"name":"1998"},{"id":41,"name":"1999"},{"id":42,"name":"2000"},{"id":43,"name":"2001"},{"id":44,"name":"2002"},{"id":45,"name":"2003"},{"id":46,"name":"2004"},{"id":47,"name":"2005"},{"id":48,"name":"2006"},{"id":49,"name":"2007"},{"id":50,"name":"2008"},{"id":51,"name":"2009"},{"id":52,"name":"2010"},{"id":53,"name":"2011"},{"id":54,"name":"2012"},{"id":55,"name":"2013"},{"id":56,"name":"2014"},{"id":57,"name":"2015"},{"id":58,"name":"2016"},{"id":59,"name":"2017"},{"id":60,"name":"2018"},{"id":61,"name":"Last Inventory Year (2019)"}],"data":[{"id":3,"name":"Australia","rows":[{"id":10189,"name":"4.C.2.e  Other Land Converted to Grassland","unitId":140,"cells":[{"column":0,"stringValue":"NO"},{"column":32,"stringValue":"NO"},{"column":33,"stringValue":"NO"},{"column":34,"stringValue":"NO"},{"column":35,"stringValue":"NO"},{"column":36,"stringValue":"NO"},{"column":37,"stringValue":"NO"},{"column":38,"stringValue":"NO"},{"column":39,"stringValue":"NO"},{"column":40,"stringValue":"NO"},{"column":41,"stringValue":"NO"},{"column":42,"stringValue":"NO"},{"column":43,"stringValue":"NO"},{"column":44,"stringValue":"NO"},{"column":45,"stringValue":"NO"},{"column":46,"stringValue":"NO"},{"column":47,"stringValue":"NO"},{"column":48,"stringValue":"NO"},{"column":49,"stringValue":"NO"},{"column":50,"stringValue":"NO"},{"column":51,"stringValue":"NO"},{"column":52,"stringValue":"NO"},{"column":53,"stringValue":"NO"},{"column":54,"stringValue":"NO"},{"column":55,"stringValue":"NO"},{"column":56,"stringValue":"NO"},{"column":57,"stringValue":"NO"},{"column":58,"stringValue":"NO"},{"column":59,"stringValue":"NO"},{"column":60,"stringValue":"NO"},{"column":61,"stringValue":"NO"}],"excludeFromChart":true}]},{"id":4,"name":"Austria","rows":[{"id":10189,"name":"4.C.2.e  Other Land Converted to Grassland","unitId":140,"cells":[{"column":0,"stringValue":"NO"},{"column":32,"stringValue":"NO"},{"column":33,"stringValue":"NO"},{"column":34,"stringValue":"NO"},{"column":35,"stringValue":"NO"},{"column":36,"stringValue":"NO"},{"column":37,"stringValue":"NO"},{"column":38,"stringValue":"NO"},{"column":39,"stringValue":"NO"},{"column":40,"stringValue":"NO"},{"column":41,"stringValue":"NO"},{"column":42,"stringValue":"NO"},{"column":43,"stringValue":"NO"},{"column":44,"stringValue":"NO"},{"column":45,"stringValue":"NO"},{"column":46,"stringValue":"NO"},{"column":47,"stringValue":"NO"},{"column":48,"stringValue":"NO"},{"column":49,"stringValue":"NO"},{"column":50,"stringValue":"NO"},{"column":51,"stringValue":"NO"},{"column":52,"stringValue":"NO"},{"column":53,"stringValue":"NO"},{"column":54,"stringValue":"NO"},{"column":55,"stringValue":"NO"},{"column":56,"stringValue":"NO"},{"column":57,"stringValue":"NO"},{"column":58,"stringValue":"NO"},{"column":59,"stringValue":"NO"},{"column":60,"stringValue":"NO"},{"column":61,"stringValue":"NO"}],"excludeFromChart":true}]},{"id":7,"name":"Belarus","rows":[{"id":10189,"name":"4.C.2.e  Other Land Converted to Grassland","unitId":140,"cells":[{"column":0,"stringValue":"IE,NE"},{"column":32,"stringValue":"IE,NE"},{"column":33,"stringValue":"IE,NE"},{"column":34,"stringValue":"IE,NE"},{"column":35,"stringValue":"IE,NE"},{"column":36,"stringValue":"IE,NE"},{"column":37,"stringValue":"IE,NE"},{"column":38,"stringValue":"IE,NE"},{"column":39,"stringValue":"IE,NE"},{"column":40,"stringValue":"IE,NE"},{"column":41,"stringValue":"IE,NE"},{"column":42,"stringValue":"IE,NE"},{"column":43,"stringValue":"IE,NE"},{"column":44,"stringValue":"IE,NE"},{"column":45,"stringValue":"IE,NE"},{"column":46,"stringValue":"IE,NE"},{"column":47,"stringValue":"IE,NE"},{"column":48,"stringValue":"IE,NE"},{"column":49,"stringValue":"IE,NE"},{"column":50,"stringValue":"IE,NE"},{"column":51,"stringValue":"IE,NE"},{"column":52,"stringValue":"IE,NE"},{"column":53,"stringValue":"IE,NE"},{"column":54,"stringValue":"IE,NE"},{"column":55,"stringValue":"IE,NE"},{"column":56,"stringValue":"IE,NE"},{"column":57,"stringValue":"IE,NE"},{"column":58,"stringValue":"IE,NE"},{"column":59,"stringValue":"IE,NE"},{"column":60,"stringValue":"IE,NE"},{"column":61,"stringValue":"IE,NE"}],"excludeFromChart":true}]},{"id":5,"name":"Belgium","rows":[{"id":10189,"name":"4.C.2.e  Other Land Converted to Grassland","unitId":140,"cells":[{"column":0,"stringValue":"NO"},{"column":32,"stringValue":"NO"},{"column":33,"stringValue":"NO"},{"column":34,"stringValue":"NO"},{"column":35,"stringValue":"NO"},{"column":36,"stringValue":"NO"},{"column":37,"stringValue":"NO"},{"column":38,"stringValue":"NO"},{"column":39,"stringValue":"NO"},{"column":40,"stringValue":"NO"},{"column":41,"stringValue":"NO"},{"column":42,"stringValue":"NO"},{"column":43,"stringValue":"NO"},{"column":44,"stringValue":"NO"},{"column":45,"stringValue":"NO"},{"column":46,"stringValue":"NO"},{"column":47,"stringValue":"NO"},{"column":48,"stringValue":"NO"},{"column":49,"stringValue":"NO"},{"column":50,"stringValue":"NO"},{"column":51,"stringValue":"NO"},{"column":52,"stringValue":"NO"},{"column":53,"stringValue":"NO"},{"column":54,"stringValue":"NO"},{"column":55,"stringValue":"NO"},{"column":56,"stringValue":"NO"},{"column":57,"stringValue":"NO"},{"column":58,"stringValue":"NO"},{"column":59,"stringValue":"NO"},{"column":60,"stringValue":"NO"},{"column":61,"stringValue":"NO"}],"excludeFromChart":true}]},{"id":6,"name":"Bulgaria","rows":[{"id":10189,"name":"4.C.2.e  Other Land Converted to Grassland","unitId":140,"cells":[{"column":0,"numberValue":-451.47968330714599},{"column":32,"numberValue":-473.97212165223681},{"column":33,"numberValue":-485.31255747526410},{"column":34,"numberValue":-496.67551803644528},{"column":35,"numberValue":-507.82850451746697},{"column":36,"numberValue":-519.13559206059983},{"column":37,"numberValue":-526.98153744603883},{"column":38,"numberValue":-537.74329061904268},{"column":39,"numberValue":-544.98758315979228},{"column":40,"numberValue":-555.25364465105781},{"column":41,"numberValue":-565.30866875110894},{"column":42,"numberValue":-482.69855058182691},{"column":43,"numberValue":-474.45970485124070},{"column":44,"numberValue":-465.54020949503456},{"column":45,"numberValue":-456.43698451134691},{"column":46,"numberValue":-447.29598033216416},{"column":47,"numberValue":-438.21803338148527},{"column":48,"numberValue":-429.24091581923233},{"column":49,"numberValue":-420.35865203563515},{"column":50,"numberValue":-400.01196968113464},{"column":51,"numberValue":-380.05972867891944},{"column":52,"numberValue":-359.70105639623119},{"column":53,"numberValue":-339.42254533328344},{"column":54,"numberValue":-318.41589926161174},{"column":55,"numberValue":-301.95928431189560},{"column":56,"numberValue":-282.40445330956237},{"column":57,"numberValue":-301.82660842736522},{"column":58,"numberValue":-306.71339001763351},{"column":59,"numberValue":-249.44503831222497},{"column":60,"numberValue":-318.69173793292981},{"column":61,"numberValue":-412.34528923382015}],"excludeFromChart":true}]},{"id":9,"name":"Canada","rows":[{"id":10189,"name":"4.C.2.e  Other Land Converted to Grassland","unitId":140,"cells":[{"column":0,"stringValue":"NO"},{"column":32,"stringValue":"NO"},{"column":33,"stringValue":"NO"},{"column":34,"stringValue":"NO"},{"column":35,"stringValue":"NO"},{"column":36,"stringValue":"NO"},{"column":37,"stringValue":"NO"},{"column":38,"stringValue":"NO"},{"column":39,"stringValue":"NO"},{"column":40,"stringValue":"NO"},{"column":41,"stringValue":"NO"},{"column":42,"stringValue":"NO"},{"column":43,"stringValue":"NO"},{"column":44,"stringValue":"NO"},{"column":45,"stringValue":"NO"},{"column":46,"stringValue":"NO"},{"column":47,"stringValue":"NO"},{"column":48,"stringValue":"NO"},{"column":49,"stringValue":"NO"},{"column":50,"stringValue":"NO"},{"column":51,"stringValue":"NO"},{"column":52,"stringValue":"NO"},{"column":53,"stringValue":"NO"},{"column":54,"stringValue":"NO"},{"column":55,"stringValue":"NO"},{"column":56,"stringValue":"NO"},{"column":57,"stringValue":"NO"},{"column":58,"stringValue":"NO"},{"column":59,"stringValue":"NO"},{"column":60,"stringValue":"NO"},{"column":61,"stringValue":"NO"}],"excludeFromChart":true}]},{"id":30,"name":"Croatia","rows":[{"id":10189,"name":"4.C.2.e  Other Land Converted to Grassland","unitId":140,"cells":[{"column":0,"stringValue":"NO"},{"column":32,"stringValue":"NO"},{"column":33,"stringValue":"NO"},{"column":34,"stringValue":"NO"},{"column":35,"stringValue":"NO"},{"column":36,"stringValue":"NO"},{"column":37,"stringValue":"NO"},{"column":38,"stringValue":"NO"},{"column":39,"stringValue":"NO"},{"column":40,"stringValue":"NO"},{"column":41,"stringValue":"NO"},{"column":42,"stringValue":"NO"},{"column":43,"stringValue":"NO"},{"column":44,"stringValue":"NO"},{"column":45,"stringValue":"NO"},{"column":46,"stringValue":"NO"},{"column":47,"stringValue":"NO"},{"column":48,"stringValue":"NO"},{"column":49,"stringValue":"NO"},{"column":50,"stringValue":"NO"},{"column":51,"stringValue":"NO"},{"column":52,"stringValue":"NO"},{"column":53,"stringValue":"NO"},{"column":54,"stringValue":"NO"},{"column":55,"stringValue":"NO"},{"column":56,"stringValue":"NO"},{"column":57,"stringValue":"NO"},{"column":58,"stringValue":"NO"},{"column":59,"stringValue":"NO"},{"column":60,"stringValue":"NO"},{"column":61,"stringValue":"NO"}],"excludeFromChart":true}]},{"id":11,"name":"Cyprus","rows":[{"id":10189,"name":"4.C.2.e  Other Land Converted to Grassland","unitId":140,"cells":[{"column":0,"stringValue":"NO"},{"column":32,"stringValue":"NO"},{"column":33,"stringValue":"NO"},{"column":34,"stringValue":"NO"},{"column":35,"stringValue":"NO"},{"column":36,"stringValue":"NO"},{"column":37,"stringValue":"NO"},{"column":38,"stringValue":"NO"},{"column":39,"stringValue":"NO"},{"column":40,"stringValue":"NO"},{"column":41,"stringValue":"NO"},{"column":42,"stringValue":"NO"},{"column":43,"stringValue":"NO"},{"column":44,"stringValue":"NO"},{"column":45,"stringValue":"NO"},{"column":46,"stringValue":"NO"},{"column":47,"stringValue":"NO"},{"column":48,"numberValue":-3.61705433542464},{"column":49,"numberValue":-3.82489726323980},{"column":50,"numberValue":-4.03274019105500},{"column":51,"numberValue":-4.24058311887016},{"column":52,"numberValue":-4.44842604668536},{"column":53,"numberValue":-4.65626897450052},{"column":54,"numberValue":-4.86411190231571},{"column":55,"numberValue":-5.07195483013087},{"column":56,"numberValue":-5.27979775794607},{"column":57,"numberValue":-5.48764068576127},{"column":58,"numberValue":-5.69548361357643},{"column":59,"numberValue":-5.90332655000001},{"column":60,"numberValue":-6.11116948642358},{"column":61,"numberValue":-6.31901242284716}],"excludeFromChart":true}]},{"id":12,"name":"Czechia","rows":[{"id":10189,"name":"4.C.2.e  Other Land Converted to Grassland","unitId":140,"cells":[{"column":0,"stringValue":"NO"},{"column":32,"stringValue":"NO"},{"column":33,"stringValue":"NO"},{"column":34,"stringValue":"NO"},{"column":35,"stringValue":"NO"},{"column":36,"stringValue":"NO"},{"column":37,"stringValue":"NO"},{"column":38,"stringValue":"NO"},{"column":39,"stringValue":"NO"},{"column":40,"stringValue":"NO"},{"column":41,"stringValue":"NO"},{"column":42,"stringValue":"NO"},{"column":43,"stringValue":"NO"},{"column":44,"stringValue":"NO"},{"column":45,"stringValue":"NO"},{"column":46,"stringValue":"NO"},{"column":47,"stringValue":"NO"},{"column":48,"stringValue":"NO"},{"column":49,"stringValue":"NO"},{"column":50,"stringValue":"NO"},{"column":51,"stringValue":"NO"},{"column":52,"stringValue":"NO"},{"column":53,"stringValue":"NO"},{"column":54,"stringValue":"NO"},{"column":55,"stringValue":"NO"},{"column":56,"stringValue":"NO"},{"column":57,"stringValue":"NO"},{"column":58,"stringValue":"NO"},{"column":59,"stringValue":"NO"},{"column":60,"stringValue":"NO"},{"column":61,"stringValue":"NO"}],"excludeFromChart":true}]},{"id":15,"name":"Denmark","rows":[{"id":10189,"name":"4.C.2.e  Other Land Converted to Grassland","unitId":140,"cells":[{"column":0,"stringValue":"NO"},{"column":32,"stringValue":"NO"},{"column":33,"stringValue":"NO"},{"column":34,"stringValue":"NO"},{"column":35,"stringValue":"NO"},{"column":36,"stringValue":"NO"},{"column":37,"stringValue":"NO"},{"column":38,"stringValue":"NO"},{"column":39,"stringValue":"NO"},{"column":40,"stringValue":"NO"},{"column":41,"stringValue":"NO"},{"column":42,"stringValue":"NO"},{"column":43,"stringValue":"NO"},{"column":44,"stringValue":"NO"},{"column":45,"stringValue":"NO"},{"column":46,"stringValue":"NO"},{"column":47,"stringValue":"NO"},{"column":48,"stringValue":"NO"},{"column":49,"stringValue":"NO"},{"column":50,"stringValue":"NO"},{"column":51,"stringValue":"NO"},{"column":52,"stringValue":"NO"},{"column":53,"stringValue":"NO"},{"column":54,"stringValue":"NO"},{"column":55,"stringValue":"NO"},{"column":56,"stringValue":"NO"},{"column":57,"stringValue":"NO"},{"column":58,"stringValue":"NO"},{"column":59,"stringValue":"NO"},{"column":60,"stringValue":"NO"},{"column":61,"stringValue":"NO"}],"excludeFromChart":true}]},{"id":18,"name":"Estonia","rows":[{"id":10189,"name":"4.C.2.e  Other Land Converted to Grassland","unitId":140,"cells":[{"column":0,"stringValue":"NO"},{"column":32,"stringValue":"NO"},{"column":33,"stringValue":"NO"},{"column":34,"stringValue":"NO"},{"column":35,"stringValue":"NO"},{"column":36,"stringValue":"NO"},{"column":37,"stringValue":"NO"},{"column":38,"stringValue":"NO"},{"column":39,"stringValue":"NO"},{"column":40,"stringValue":"NO"},{"column":41,"stringValue":"NO"},{"column":42,"stringValue":"NO"},{"column":43,"stringValue":"NO"},{"column":44,"numberValue":-0.01734333333333},{"column":45,"numberValue":-0.06259451391857},{"column":46,"numberValue":-0.12478569450380},{"column":47,"numberValue":-0.23077236930407},{"column":48,"numberValue":-0.36336885194918},{"column":49,"numberValue":-0.51169533459425},{"column":50,"numberValue":-0.68533358567711},{"column":51,"numberValue":-0.85776183676000},{"column":52,"numberValue":-1.01170636206559},{"column":53,"numberValue":-1.13904107952639},{"column":54,"numberValue":-1.23330246365381},{"column":55,"numberValue":-1.27434423209159},{"column":56,"numberValue":-1.29965600052937},{"column":57,"numberValue":-1.29965600052937},{"column":58,"numberValue":-1.29965600052937},{"column":59,"numberValue":-1.29965600052937},{"column":60,"numberValue":-1.29965600052937},{"column":61,"numberValue":-1.29965600052937}],"excludeFromChart":true}]},{"id":19,"name":"European Union (Convention)","rows":[{"id":10189,"name":"4.C.2.e  Other Land Converted to Grassland","unitId":140,"cells":[{"column":0,"numberValue":246.83761897811812},{"column":32,"numberValue":246.83761897811812},{"column":33,"numberValue":48.44122989154065},{"column":34,"numberValue":-29.64351863201805},{"column":35,"numberValue":-117.11384102434492},{"column":36,"numberValue":-223.48052172222503},{"column":37,"numberValue":-100.96801888939800},{"column":38,"numberValue":20.64452538257118},{"column":39,"numberValue":42.61992846165117},{"column":40,"numberValue":90.61185028818775},{"column":41,"numberValue":10.27805111249496},{"column":42,"numberValue":29.35209050440189},{"column":43,"numberValue":-124.37323297484166},{"column":44,"numberValue":-235.91846194400989},{"column":45,"numberValue":-321.91510551599328},{"column":46,"numberValue":-425.74664316353966},{"column":47,"numberValue":-479.16534237362424},{"column":48,"numberValue":-501.93925733125712},{"column":49,"numberValue":-653.67757576618635},{"column":50,"numberValue":-704.65878676183729},{"column":51,"numberValue":-676.28882979928267},{"column":52,"numberValue":-622.63641454434708},{"column":53,"numberValue":-532.49264198836931},{"column":54,"numberValue":-434.54169061038800},{"column":55,"numberValue":-323.50222305051585},{"column":56,"numberValue":-225.07247733329393},{"column":57,"numberValue":-219.97326260034467},{"column":58,"numberValue":-296.47362695438630},{"column":59,"numberValue":-153.65836689221524},{"column":60,"numberValue":-230.28822047855877},{"column":61,"numberValue":-297.91402961432510}],"excludeFromChart":true}]},{"id":20,"name":"European Union (KP)","rows":[{"id":10189,"name":"4.C.2.e  Other Land Converted to Grassland","unitId":140,"cells":[{"column":0,"numberValue":-103.14434754467717},{"column":32,"numberValue":-103.14434754467717},{"column":33,"numberValue":-307.33768542071618},{"column":34,"numberValue":-392.85757698373658},{"column":35,"numberValue":-486.10935499552505},{"column":36,"numberValue":-601.52435568286683},{"column":37,"numberValue":-490.05468073950135},{"column":38,"numberValue":-378.76297385699382},{"column":39,"numberValue":-368.73848276737550},{"column":40,"numberValue":-335.10688763030055},{"column":41,"numberValue":-428.82094979545491},{"column":42,"numberValue":-422.38192119300959},{"column":43,"numberValue":-584.53168921171471},{"column":44,"numberValue":-704.04044457034468},{"column":45,"numberValue":-801.02229473178954},{"column":46,"numberValue":-919.95504316879760},{"column":47,"numberValue":-985.87015481834385},{"column":48,"numberValue":-1020.96380406543840},{"column":49,"numberValue":-1181.20050078982920},{"column":50,"numberValue":-1241.10377487494180},{"column":51,"numberValue":-1220.31284700184870},{"column":52,"numberValue":-1177.49509563637480},{"column":53,"numberValue":-1098.53543496985870},{"column":54,"numberValue":-1008.16775538133900},{"column":55,"numberValue":-905.07979671092835},{"column":56,"numberValue":-815.95713388316813},{"column":57,"numberValue":-822.15259203968048},{"column":58,"numberValue":-914.10944628318373},{"column":59,"numberValue":-784.69181711047429},{"column":60,"numberValue":-868.73201588627956},{"column":61,"numberValue":-943.61991257817408}],"excludeFromChart":true}]},{"id":21,"name":"Finland","rows":[{"id":10189,"name":"4.C.2.e  Other Land Converted to Grassland","unitId":140,"cells":[{"column":0,"stringValue":"NA"},{"column":32,"stringValue":"NA"},{"column":33,"stringValue":"NA"},{"column":34,"stringValue":"NA"},{"column":35,"stringValue":"NA"},{"column":36,"stringValue":"NA"},{"column":37,"stringValue":"NA"},{"column":38,"stringValue":"NA"},{"column":39,"stringValue":"NA"},{"column":40,"stringValue":"NA"},{"column":41,"stringValue":"NA"},{"column":42,"stringValue":"NA"},{"column":43,"stringValue":"NA"},{"column":44,"stringValue":"NA"},{"column":45,"stringValue":"NA"},{"column":46,"stringValue":"NA"},{"column":47,"stringValue":"NA"},{"column":48,"stringValue":"NA"},{"column":49,"stringValue":"NA"},{"column":50,"stringValue":"NA"},{"column":51,"stringValue":"NA"},{"column":52,"stringValue":"NA"},{"column":53,"stringValue":"NA"},{"column":54,"stringValue":"NA"},{"column":55,"stringValue":"NA"},{"column":56,"stringValue":"NA"},{"column":57,"stringValue":"NA"},{"column":58,"stringValue":"NA"},{"column":59,"stringValue":"NA"},{"column":60,"stringValue":"NA"},{"column":61,"stringValue":"NA"}],"excludeFromChart":true}]},{"id":23,"name":"France","rows":[{"id":10189,"name":"4.C.2.e  Other Land Converted to Grassland","unitId":140,"cells":[{"column":0,"stringValue":"NE,NO"},{"column":32,"stringValue":"NE,NO"},{"column":33,"stringValue":"NE,NO"},{"column":34,"stringValue":"NE,NO"},{"column":35,"stringValue":"NE,NO"},{"column":36,"stringValue":"NE,NO"},{"column":37,"stringValue":"NE,NO"},{"column":38,"stringValue":"NE,NO"},{"column":39,"stringValue":"NE,NO"},{"column":40,"stringValue":"NE,NO"},{"column":41,"stringValue":"NE,NO"},{"column":42,"stringValue":"NE,NO"},{"column":43,"stringValue":"NE,NO"},{"column":44,"stringValue":"NE,NO"},{"column":45,"stringValue":"NE,NO"},{"column":46,"stringValue":"NE,NO"},{"column":47,"stringValue":"NE,NO"},{"column":48,"stringValue":"NE,NO"},{"column":49,"stringValue":"NE,NO"},{"column":50,"stringValue":"NE,NO"},{"column":51,"stringValue":"NE,NO"},{"column":52,"stringValue":"NE,NO"},{"column":53,"stringValue":"NE,NO"},{"column":54,"stringValue":"NE,NO"},{"column":55,"stringValue":"NE,NO"},{"column":56,"stringValue":"NE,NO"},{"column":57,"stringValue":"NE,NO"},{"column":58,"stringValue":"NE,NO"},{"column":59,"stringValue":"NE,NO"},{"column":60,"stringValue":"NE,NO"},{"column":61,"stringValue":"NE,NO"}],"excludeFromChart":true}]},{"id":13,"name":"Germany","rows":[{"id":10189,"name":"4.C.2.e  Other Land Converted to Grassland","unitId":140,"cells":[{"column":0,"numberValue":-58.10201991711339},{"column":32,"numberValue":-58.10201991711339},{"column":33,"numberValue":-58.10817446540339},{"column":34,"numberValue":-57.37544890264005},{"column":35,"numberValue":-57.20603795540339},{"column":36,"numberValue":-56.89860405207005},{"column":37,"numberValue":-56.05009995321005},{"column":38,"numberValue":-55.95321193264005},{"column":39,"numberValue":-55.46405544654338},{"column":40,"numberValue":-54.80556096825338},{"column":41,"numberValue":-54.97831589044672},{"column":42,"numberValue":-55.39646410873672},{"column":43,"numberValue":-95.37375165087008},{"column":44,"numberValue":-98.29371885468676},{"column":45,"numberValue":-100.28131479916009},{"column":46,"numberValue":-102.29247747363344},{"column":47,"numberValue":-104.63299270420345},{"column":48,"numberValue":-77.55995105067007},{"column":49,"numberValue":-78.43652026067006},{"column":50,"numberValue":-78.80105568628341},{"column":51,"numberValue":-80.69261939676674},{"column":52,"numberValue":-81.30652331457341},{"column":53,"numberValue":-90.27023279087008},{"column":54,"numberValue":-89.38368018477341},{"column":55,"numberValue":-88.74779614477340},{"column":56,"numberValue":-88.53182269030007},{"column":57,"numberValue":-87.46489795087008},{"column":58,"numberValue":-68.30082707756006},{"column":59,"numberValue":-65.71488046317339},{"column":60,"numberValue":-64.22447560870006},{"column":61,"numberValue":-61.40214651098006}],"excludeFromChart":true}]},{"id":28,"name":"Greece","rows":[{"id":10189,"name":"4.C.2.e  Other Land Converted to Grassland","unitId":140,"cells":[{"column":0,"stringValue":"NO"},{"column":32,"stringValue":"NO"},{"column":33,"stringValue":"NO"},{"column":34,"stringValue":"NO"},{"column":35,"stringValue":"NO"},{"column":36,"stringValue":"NO"},{"column":37,"stringValue":"NO"},{"column":38,"stringValue":"NO"},{"column":39,"stringValue":"NO"},{"column":40,"stringValue":"NO"},{"column":41,"stringValue":"NO"},{"column":42,"stringValue":"NO"},{"column":43,"stringValue":"NO"},{"column":44,"stringValue":"NO"},{"column":45,"stringValue":"NO"},{"column":46,"stringValue":"NO"},{"column":47,"stringValue":"NO"},{"column":48,"stringValue":"NO"},{"column":49,"stringValue":"NO"},{"column":50,"stringValue":"NO"},{"column":51,"stringValue":"NO"},{"column":52,"stringValue":"NO"},{"column":53,"stringValue":"NO"},{"column":54,"stringValue":"NO"},{"column":55,"stringValue":"NO"},{"column":56,"stringValue":"NO"},{"column":57,"stringValue":"NO"},{"column":58,"stringValue":"NO"},{"column":59,"stringValue":"NO"},{"column":60,"stringValue":"NO"},{"column":61,"stringValue":"NO"}],"excludeFromChart":true}]},{"id":31,"name":"Hungary","rows":[{"id":10189,"name":"4.C.2.e  Other Land Converted to Grassland","unitId":140,"cells":[{"column":0,"stringValue":"NO"},{"column":32,"stringValue":"NO"},{"column":33,"stringValue":"NO"},{"column":34,"stringValue":"NO"},{"column":35,"stringValue":"NO"},{"column":36,"stringValue":"NO"},{"column":37,"stringValue":"NO"},{"column":38,"stringValue":"NO"},{"column":39,"stringValue":"NO"},{"column":40,"stringValue":"NO"},{"column":41,"stringValue":"NO"},{"column":42,"stringValue":"NO"},{"column":43,"stringValue":"NO"},{"column":44,"stringValue":"NO"},{"column":45,"stringValue":"NO"},{"column":46,"stringValue":"NO"},{"column":47,"stringValue":"NO"},{"column":48,"stringValue":"NO"},{"column":49,"stringValue":"NO"},{"column":50,"stringValue":"NO"},{"column":51,"stringValue":"NO"},{"column":52,"stringValue":"NO"},{"column":53,"stringValue":"NO"},{"column":54,"stringValue":"NO"},{"column":55,"stringValue":"NO"},{"column":56,"stringValue":"NO"},{"column":57,"stringValue":"NO"},{"column":58,"stringValue":"NO"},{"column":59,"stringValue":"NO"},{"column":60,"stringValue":"NO"},{"column":61,"stringValue":"NO"}],"excludeFromChart":true}]},{"id":33,"name":"Iceland","rows":[{"id":10189,"name":"4.C.2.e  Other Land Converted to Grassland","unitId":140,"cells":[{"column":0,"numberValue":-349.98196652279529},{"column":32,"numberValue":-349.98196652279529},{"column":33,"numberValue":-355.77891531225680},{"column":34,"numberValue":-363.21405835171856},{"column":35,"numberValue":-368.99551397118017},{"column":36,"numberValue":-378.04383396064173},{"column":37,"numberValue":-389.08666185010338},{"column":38,"numberValue":-399.40749923956497},{"column":39,"numberValue":-411.35841122902661},{"column":40,"numberValue":-425.71873791848833},{"column":41,"numberValue":-439.09900090794986},{"column":42,"numberValue":-451.73401169741152},{"column":43,"numberValue":-460.15845623687306},{"column":44,"numberValue":-468.12198262633473},{"column":45,"numberValue":-479.10718921579632},{"column":46,"numberValue":-494.20840000525800},{"column":47,"numberValue":-506.70481244471961},{"column":48,"numberValue":-519.02454673418129},{"column":49,"numberValue":-527.52292502364276},{"column":50,"numberValue":-536.44498811310450},{"column":51,"numberValue":-544.02401720256603},{"column":52,"numberValue":-554.85868109202772},{"column":53,"numberValue":-566.04279298148936},{"column":54,"numberValue":-573.62606477095096},{"column":55,"numberValue":-581.57757366041255},{"column":56,"numberValue":-590.88465654987419},{"column":57,"numberValue":-602.17932943933579},{"column":58,"numberValue":-617.63581932879742},{"column":59,"numberValue":-631.03345021825908},{"column":60,"numberValue":-638.44379540772070},{"column":61,"numberValue":-645.70588296384892}],"excludeFromChart":true}]},{"id":32,"name":"Ireland","rows":[{"id":10189,"name":"4.C.2.e  Other Land Converted to Grassland","unitId":140,"cells":[{"column":0,"stringValue":"NO"},{"column":32,"stringValue":"NO"},{"column":33,"stringValue":"NO"},{"column":34,"stringValue":"NO"},{"column":35,"stringValue":"NO"},{"column":36,"stringValue":"NO"},{"column":37,"stringValue":"NO"},{"column":38,"stringValue":"NO"},{"column":39,"stringValue":"NO"},{"column":40,"stringValue":"NO"},{"column":41,"stringValue":"NO"},{"column":42,"stringValue":"NO"},{"column":43,"stringValue":"NO"},{"column":44,"stringValue":"NO"},{"column":45,"stringValue":"NO"},{"column":46,"stringValue":"NO"},{"column":47,"stringValue":"NO"},{"column":48,"stringValue":"NO"},{"column":49,"stringValue":"NO"},{"column":50,"stringValue":"NO"},{"column":51,"stringValue":"NO"},{"column":52,"stringValue":"NO"},{"column":53,"stringValue":"NO"},{"column":54,"stringValue":"NO"},{"column":55,"stringValue":"NO"},{"column":56,"stringValue":"NO"},{"column":57,"stringValue":"NO"},{"column":58,"stringValue":"NO"},{"column":59,"stringValue":"NO"},{"column":60,"stringValue":"NO"},{"column":61,"stringValue":"NO"}],"excludeFromChart":true}]},{"id":34,"name":"Italy","rows":[{"id":10189,"name":"4.C.2.e  Other Land Converted to Grassland","unitId":140,"cells":[{"column":0,"stringValue":"NO"},{"column":32,"stringValue":"NO"},{"column":33,"stringValue":"NO"},{"column":34,"stringValue":"NO"},{"column":35,"stringValue":"NO"},{"column":36,"stringValue":"NO"},{"column":37,"stringValue":"NO"},{"column":38,"stringValue":"NO"},{"column":39,"stringValue":"NO"},{"column":40,"stringValue":"NO"},{"column":41,"stringValue":"NO"},{"column":42,"stringValue":"NO"},{"column":43,"stringValue":"NO"},{"column":44,"stringValue":"NO"},{"column":45,"stringValue":"NO"},{"column":46,"stringValue":"NO"},{"column":47,"stringValue":"NO"},{"column":48,"stringValue":"NO"},{"column":49,"stringValue":"NO"},{"column":50,"stringValue":"NO"},{"column":51,"stringValue":"NO"},{"column":52,"stringValue":"NO"},{"column":53,"stringValue":"NO"},{"column":54,"stringValue":"NO"},{"column":55,"stringValue":"NO"},{"column":56,"stringValue":"NO"},{"column":57,"stringValue":"NO"},{"column":58,"stringValue":"NO"},{"column":59,"stringValue":"NO"},{"column":60,"stringValue":"NO"},{"column":61,"stringValue":"NO"}],"excludeFromChart":true}]},{"id":35,"name":"Japan","rows":[{"id":10189,"name":"4.C.2.e  Other Land Converted to Grassland","unitId":140,"cells":[{"column":0,"numberValue":-0.31502462729595},{"column":32,"numberValue":-0.31502462729595},{"column":33,"numberValue":-0.37834708974880},{"column":34,"numberValue":-0.33264515538778},{"column":35,"numberValue":-0.67254709329647},{"column":36,"numberValue":-0.91016973081987},{"column":37,"numberValue":-0.93552793560937},{"column":38,"numberValue":-0.85177280342550},{"column":39,"numberValue":-0.85601151086942},{"column":40,"numberValue":-0.50249495016937},{"column":41,"numberValue":-0.22480980654675},{"column":42,"numberValue":-0.20564921937472},{"column":43,"numberValue":-0.20095429018155},{"column":44,"numberValue":-0.26327468755969},{"column":45,"numberValue":-0.26779458149565},{"column":46,"numberValue":-1.04307696418783},{"column":47,"numberValue":-1.19016601129276},{"column":48,"numberValue":-1.34373389188698},{"column":49,"numberValue":-1.29794356366209},{"column":50,"numberValue":-1.28673805888133},{"column":51,"numberValue":-0.42407836931222},{"column":52,"numberValue":-0.25092577929316},{"column":53,"numberValue":-0.07121146640007},{"column":54,"numberValue":-0.28802499102997},{"column":55,"numberValue":-0.96599008093709},{"column":56,"numberValue":-1.59750981564988},{"column":57,"numberValue":-2.17441505537982},{"column":58,"numberValue":-2.67843044285154},{"column":59,"numberValue":-5.59601528904760},{"column":60,"numberValue":-11.50545604733126},{"column":61,"numberValue":-17.64140429568005}],"excludeFromChart":true}]},{"id":36,"name":"Kazakhstan","rows":[{"id":10189,"name":"4.C.2.e  Other Land Converted to Grassland","unitId":140,"cells":[{"column":0,"stringValue":"NO"},{"column":32,"stringValue":"NO"},{"column":33,"stringValue":"NO"},{"column":34,"stringValue":"NO"},{"column":35,"stringValue":"NO"},{"column":36,"stringValue":"NO"},{"column":37,"stringValue":"NO"},{"column":38,"stringValue":"NO"},{"column":39,"stringValue":"NO"},{"column":40,"stringValue":"NO"},{"column":41,"stringValue":"NO"},{"column":42,"stringValue":"NO"},{"column":43,"stringValue":"NO"},{"column":44,"stringValue":"NO"},{"column":45,"stringValue":"NO"},{"column":46,"stringValue":"NO"},{"column":47,"stringValue":"NO"},{"column":48,"stringValue":"NO"},{"column":49,"stringValue":"NO"},{"column":50,"stringValue":"NO"},{"column":51,"stringValue":"NO"},{"column":52,"stringValue":"NO"},{"column":53,"stringValue":"NO"},{"column":54,"stringValue":"NO"},{"column":55,"stringValue":"NO"},{"column":56,"stringValue":"NO"},{"column":57,"stringValue":"NO"},{"column":58,"stringValue":"NO"},{"column":59,"stringValue":"NO"},{"column":60,"stringValue":"NO"},{"column":61,"stringValue":"NO"}],"excludeFromChart":true}]},{"id":41,"name":"Latvia","rows":[{"id":10189,"name":"4.C.2.e  Other Land Converted to Grassland","unitId":140,"cells":[{"column":0,"stringValue":"NO"},{"column":32,"stringValue":"NO"},{"column":33,"stringValue":"NO"},{"column":34,"stringValue":"NO"},{"column":35,"stringValue":"NO"},{"column":36,"stringValue":"NO"},{"column":37,"stringValue":"NO"},{"column":38,"stringValue":"NO"},{"column":39,"stringValue":"NO"},{"column":40,"stringValue":"NO"},{"column":41,"stringValue":"NO"},{"column":42,"stringValue":"NO"},{"column":43,"stringValue":"NO"},{"column":44,"stringValue":"NO"},{"column":45,"stringValue":"NO"},{"column":46,"stringValue":"NO"},{"column":47,"stringValue":"NO"},{"column":48,"stringValue":"NO"},{"column":49,"stringValue":"NO"},{"column":50,"stringValue":"NO"},{"column":51,"stringValue":"NO"},{"column":52,"stringValue":"NO"},{"column":53,"stringValue":"NO"},{"column":54,"stringValue":"NO"},{"column":55,"stringValue":"NO"},{"column":56,"stringValue":"NO"},{"column":57,"stringValue":"NO"},{"column":58,"stringValue":"NO"},{"column":59,"stringValue":"NO"},{"column":60,"stringValue":"NO"},{"column":61,"stringValue":"NO"}],"excludeFromChart":true}]},{"id":38,"name":"Liechtenstein","rows":[{"id":10189,"name":"4.C.2.e  Other Land Converted to Grassland","unitId":140,"cells":[{"column":0,"numberValue":-0.22692231354874},{"column":32,"numberValue":-0.22692231354874},{"column":33,"numberValue":-0.22692231354874},{"column":34,"numberValue":-0.22692231354874},{"column":35,"numberValue":-0.22692231354874},{"column":36,"numberValue":-0.22692231354874},{"column":37,"numberValue":-0.22692231354874},{"column":38,"numberValue":-0.22692231354874},{"column":39,"numberValue":-0.23407628197965},{"column":40,"numberValue":-0.24123025041056},{"column":41,"numberValue":-0.24838421884148},{"column":42,"numberValue":-0.25553818727239},{"column":43,"numberValue":-0.26269215570330},{"column":44,"numberValue":-0.26984612413418},{"column":45,"numberValue":-0.27456899634813},{"column":46,"numberValue":-0.27929186856204},{"column":47,"numberValue":-0.28401474077592},{"column":48,"numberValue":-0.28873761298987},{"column":49,"numberValue":-0.29346048520378},{"column":50,"numberValue":-0.29818335741766},{"column":51,"numberValue":-0.31730167917998},{"column":52,"numberValue":-0.33642000094226},{"column":53,"numberValue":-0.35553832270455},{"column":54,"numberValue":-0.37465664446683},{"column":55,"numberValue":-0.39377496622911},{"column":56,"numberValue":-0.41289328799140},{"column":57,"numberValue":-0.43201160975364},{"column":58,"numberValue":-0.45126718716911},{"column":59,"numberValue":-0.46323154050048},{"column":60,"numberValue":-0.47519589383185},{"column":61,"numberValue":-0.48716024716322}],"excludeFromChart":true}]},{"id":39,"name":"Lithuania","rows":[{"id":10189,"name":"4.C.2.e  Other Land Converted to Grassland","unitId":140,"cells":[{"column":0,"stringValue":"NO"},{"column":32,"stringValue":"NO"},{"column":33,"numberValue":-188.15089443014088},{"column":34,"numberValue":-271.12727021353243},{"column":35,"numberValue":-360.09198681665271},{"column":36,"numberValue":-420.83579070674864},{"column":37,"numberValue":-475.59125377711598},{"column":38,"numberValue":-370.41673513036670},{"column":39,"numberValue":-359.30044918371885},{"column":40,"numberValue":-359.30044918371885},{"column":41,"numberValue":-359.30044918371885},{"column":42,"numberValue":-359.30044918371880},{"column":43,"numberValue":-370.41673513036665},{"column":44,"numberValue":-359.30044918371880},{"column":45,"numberValue":-359.30044918371880},{"column":46,"numberValue":-359.30044918371880},{"column":47,"numberValue":-359.30044918371880},{"column":48,"numberValue":-359.30044918371880},{"column":49,"numberValue":-359.30044918371885},{"column":50,"numberValue":-359.30044918371885},{"column":51,"numberValue":-376.40507595009535},{"column":52,"numberValue":-365.28879000344750},{"column":53,"numberValue":-299.41704098643243},{"column":54,"numberValue":-233.54529196941729},{"column":55,"numberValue":-155.70301043128532},{"column":56,"numberValue":-100.94122865867496},{"column":57,"numberValue":-75.27127273793965},{"column":58,"numberValue":-76.12881225879823},{"column":59,"numberValue":-65.01509656783132},{"column":60,"numberValue":-71.00649125826519},{"column":61,"numberValue":-59.88813707152208}],"excludeFromChart":true}]},{"id":40,"name":"Luxembourg","rows":[{"id":10189,"name":"4.C.2.e  Other Land Converted to Grassland","unitId":140,"cells":[{"column":0,"numberValue":-7.45183455313892},{"column":32,"numberValue":-7.45183455313892},{"column":33,"numberValue":-7.45183455313892},{"column":34,"numberValue":-7.45183455313892},{"column":35,"numberValue":-7.45183455313892},{"column":36,"numberValue":-7.45183455313892},{"column":37,"numberValue":-7.45183455313892},{"column":38,"numberValue":-7.45183455313892},{"column":39,"numberValue":-7.45183455313892},{"column":40,"numberValue":-7.45183455313892},{"column":41,"numberValue":-7.45183455313892},{"column":42,"numberValue":-6.66566815809107},{"column":43,"numberValue":-6.31615591965923},{"column":44,"numberValue":-5.96664368122736},{"column":45,"numberValue":-5.61713144279552},{"column":46,"numberValue":-5.26761920436367},{"column":47,"numberValue":-4.91810696593180},{"column":48,"numberValue":-4.56859472749996},{"column":49,"numberValue":-4.21908248906808},{"column":50,"numberValue":-3.86693071657490},{"column":51,"numberValue":-3.51624499952074},{"column":52,"numberValue":-3.16555928246654},{"column":53,"numberValue":-2.81487356541234},{"column":54,"numberValue":-2.46418784835814},{"column":55,"numberValue":-2.11350213130394},{"column":56,"numberValue":-1.76281641424973},{"column":57,"numberValue":-1.41213069719553},{"column":58,"numberValue":-1.06144498014133},{"column":59,"numberValue":-0.71075926308713},{"column":60,"numberValue":-0.36007354603293},{"column":61,"numberValue":-0.00938782897873}],"excludeFromChart":true}]},{"id":43,"name":"Malta","rows":[{"id":10189,"name":"4.C.2.e  Other Land Converted to Grassland","unitId":140,"cells":[{"column":0,"stringValue":"NO"},{"column":32,"stringValue":"NO"},{"column":33,"stringValue":"NO"},{"column":34,"stringValue":"NO"},{"column":35,"stringValue":"NO"},{"column":36,"stringValue":"NO"},{"column":37,"stringValue":"NO"},{"column":38,"stringValue":"NO"},{"column":39,"stringValue":"NO"},{"column":40,"stringValue":"NO"},{"column":41,"stringValue":"NO"},{"column":42,"stringValue":"NO"},{"column":43,"stringValue":"NO"},{"column":44,"stringValue":"NO"},{"column":45,"stringValue":"NO"},{"column":46,"stringValue":"NO"},{"column":47,"stringValue":"NO"},{"column":48,"stringValue":"NO"},{"column":49,"stringValue":"NO"},{"column":50,"stringValue":"NO"},{"column":51,"stringValue":"NO"},{"column":52,"stringValue":"NO"},{"column":53,"stringValue":"NO"},{"column":54,"stringValue":"NO"},{"column":55,"stringValue":"NO"},{"column":56,"stringValue":"NO"},{"column":57,"stringValue":"NO"},{"column":58,"stringValue":"NO"},{"column":59,"stringValue":"NO"},{"column":60,"stringValue":"NO"},{"column":61,"stringValue":"NO"}],"excludeFromChart":true}]},{"id":42,"name":"Monaco","rows":[{"id":10189,"name":"4.C.2.e  Other Land Converted to Grassland","unitId":140,"cells":[{"column":0,"stringValue":"NO"},{"column":32,"stringValue":"NO"},{"column":33,"stringValue":"NO"},{"column":34,"stringValue":"NO"},{"column":35,"stringValue":"NO"},{"column":36,"stringValue":"NO"},{"column":37,"stringValue":"NO"},{"column":38,"stringValue":"NO"},{"column":39,"stringValue":"NO"},{"column":40,"stringValue":"NO"},{"column":41,"stringValue":"NO"},{"column":42,"stringValue":"NO"},{"column":43,"stringValue":"NO"},{"column":44,"stringValue":"NO"},{"column":45,"stringValue":"NO"},{"column":46,"stringValue":"NO"},{"column":47,"stringValue":"NO"},{"column":48,"stringValue":"NO"},{"column":49,"stringValue":"NO"},{"column":50,"stringValue":"NO"},{"column":51,"stringValue":"NO"},{"column":52,"stringValue":"NO"},{"column":53,"stringValue":"NO"},{"column":54,"stringValue":"NO"},{"column":55,"stringValue":"NO"},{"column":56,"stringValue":"NO"},{"column":57,"stringValue":"NO"},{"column":58,"stringValue":"NO"},{"column":59,"stringValue":"NO"},{"column":60,"stringValue":"NO"},{"column":61,"stringValue":"NO"}],"excludeFromChart":true}]},{"id":44,"name":"Netherlands","rows":[{"id":10189,"name":"4.C.2.e  Other Land Converted to Grassland","unitId":140,"cells":[{"column":0,"numberValue":-39.86155728252786},{"column":32,"numberValue":-39.86155728252786},{"column":33,"numberValue":-40.67443065698544},{"column":34,"numberValue":-41.52832070777577},{"column":35,"numberValue":-42.42398910826747},{"column":36,"numberValue":-43.36116791825504},{"column":37,"numberValue":-44.33349051264837},{"column":38,"numberValue":-45.35646035266871},{"column":39,"numberValue":-46.41529480049738},{"column":40,"numberValue":-47.51637176538271},{"column":41,"numberValue":-48.66419924203571},{"column":42,"numberValue":-49.84547003472671},{"column":43,"numberValue":-51.06959693914838},{"column":44,"numberValue":-52.35538617644138},{"column":45,"numberValue":-53.68069393662438},{"column":46,"numberValue":-49.43523855691304},{"column":47,"numberValue":-47.21802337432771},{"column":48,"numberValue":-45.01506312503204},{"column":49,"numberValue":-42.81039141149471},{"column":50,"numberValue":-40.65517659510637},{"column":51,"numberValue":-44.78546444974071},{"column":52,"numberValue":-45.06349452394537},{"column":53,"numberValue":-45.48667999998471},{"column":54,"numberValue":-46.12639909568171},{"column":55,"numberValue":-42.21261881271237},{"column":56,"numberValue":-40.07002967517370},{"column":57,"numberValue":-38.05933598337937},{"column":58,"numberValue":-36.24963071127937},{"column":59,"numberValue":-36.25727901959170},{"column":60,"numberValue":-36.66750924134470},{"column":61,"numberValue":-37.17513436147503}],"excludeFromChart":true}]},{"id":46,"name":"New Zealand","rows":[{"id":10189,"name":"4.C.2.e  Other Land Converted to Grassland","unitId":140,"cells":[{"column":0,"numberValue":-2.27408192272635},{"column":32,"numberValue":-2.27408192272635},{"column":33,"numberValue":-3.16386683027177},{"column":34,"numberValue":-4.05365173781114},{"column":35,"numberValue":-4.94343664539084},{"column":36,"numberValue":-5.83322155288987},{"column":37,"numberValue":-6.72300646049524},{"column":38,"numberValue":-7.61279136803131},{"column":39,"numberValue":-9.03919998980827},{"column":40,"numberValue":-10.12614561877821},{"column":41,"numberValue":-11.21309124767518},{"column":42,"numberValue":-12.30003687697474},{"column":43,"numberValue":-13.38698250594871},{"column":44,"numberValue":-13.93730442107668},{"column":45,"numberValue":-14.82708932842575},{"column":46,"numberValue":-15.71687423607108},{"column":47,"numberValue":-16.60665914382348},{"column":48,"numberValue":-17.49644405113882},{"column":49,"numberValue":-18.38622895882155},{"column":50,"numberValue":-18.54261608753952},{"column":51,"numberValue":-18.94594165010215},{"column":52,"numberValue":-18.46054268059450},{"column":53,"numberValue":-17.97614517551803},{"column":54,"numberValue":-17.49269022539095},{"column":55,"numberValue":-16.11581616610032},{"column":56,"numberValue":-15.40031163439697},{"column":57,"numberValue":-14.69915289470021},{"column":58,"numberValue":-14.01233994700992},{"column":59,"numberValue":-12.93677100976899},{"column":60,"numberValue":-12.08699462656771},{"column":61,"numberValue":-11.29550269512475}],"excludeFromChart":true}]},{"id":45,"name":"Norway","rows":[{"id":10189,"name":"4.C.2.e  Other Land Converted to Grassland","unitId":140,"cells":[{"column":0,"stringValue":"NO"},{"column":32,"stringValue":"NO"},{"column":33,"stringValue":"NO"},{"column":34,"stringValue":"NO"},{"column":35,"stringValue":"NO"},{"column":36,"stringValue":"NO"},{"column":37,"stringValue":"NO"},{"column":38,"stringValue":"NO"},{"column":39,"stringValue":"NO"},{"column":40,"stringValue":"NO"},{"column":41,"stringValue":"NO"},{"column":42,"stringValue":"NO"},{"column":43,"stringValue":"NO"},{"column":44,"stringValue":"NO"},{"column":45,"stringValue":"NO"},{"column":46,"stringValue":"NO"},{"column":47,"stringValue":"NO"},{"column":48,"stringValue":"NO"},{"column":49,"stringValue":"NO"},{"column":50,"stringValue":"NO"},{"column":51,"stringValue":"NO"},{"column":52,"stringValue":"NO"},{"column":53,"stringValue":"NO"},{"column":54,"stringValue":"NO"},{"column":55,"stringValue":"NO"},{"column":56,"stringValue":"NO"},{"column":57,"stringValue":"NO"},{"column":58,"stringValue":"NO"},{"column":59,"stringValue":"NO"},{"column":60,"stringValue":"NO"},{"column":61,"stringValue":"NO"}],"excludeFromChart":true}]},{"id":47,"name":"Poland","rows":[{"id":10189,"name":"4.C.2.e  Other Land Converted to Grassland","unitId":140,"cells":[{"column":0,"numberValue":0.44733333333333},{"column":32,"numberValue":0.44733333333333},{"column":33,"numberValue":0.44733333333333},{"column":34,"numberValue":0.44733333333333},{"column":35,"numberValue":0.44733333333333},{"column":36,"numberValue":0.44733333333333},{"column":37,"numberValue":0.44733333333333},{"column":38,"numberValue":0.44733333333333},{"column":39,"numberValue":0.44733333333333},{"column":40,"numberValue":0.44733333333333},{"column":41,"numberValue":0.44733333333333},{"column":42,"numberValue":0.44733333333333},{"column":43,"numberValue":0.42496666666667},{"column":44,"numberValue":0.40260000000000},{"column":45,"numberValue":0.38023333333333},{"column":46,"numberValue":0.35786666666667},{"column":47,"numberValue":0.33550000000000},{"column":48,"numberValue":0.31313333333333},{"column":49,"stringValue":"NO"},{"column":50,"stringValue":"NO"},{"column":51,"stringValue":"NO"},{"column":52,"stringValue":"NO"},{"column":53,"stringValue":"NO"},{"column":54,"stringValue":"NO"},{"column":55,"stringValue":"NO"},{"column":56,"stringValue":"NO"},{"column":57,"stringValue":"NO"},{"column":58,"numberValue":-89.15720000000007},{"column":59,"numberValue":-17.31290000000002},{"column":60,"numberValue":-15.90526666666668},{"column":61,"numberValue":0.02236666666667}],"excludeFromChart":true}]},{"id":48,"name":"Portugal","rows":[{"id":10189,"name":"4.C.2.e  Other Land Converted to Grassland","unitId":140,"cells":[{"column":0,"numberValue":1385.53851287101404},{"column":32,"numberValue":1385.53851287101404},{"column":33,"numberValue":1371.25841720474299},{"column":34,"numberValue":1356.97832153847520},{"column":35,"numberValue":1342.69822587220413},{"column":36,"numberValue":1332.82123662662680},{"column":37,"numberValue":1482.65901224855811},{"column":38,"numberValue":1494.35878134612080},{"column":39,"numberValue":1506.05855044368320},{"column":40,"numberValue":1517.75831954124888},{"column":41,"numberValue":1392.08486064564293},{"column":42,"numberValue":1266.41140175004013},{"column":43,"numberValue":1140.73794285443408},{"column":44,"numberValue":1015.06448395883135},{"column":45,"numberValue":889.39102506322869},{"column":46,"numberValue":763.71756616762282},{"column":47,"numberValue":682.84133045780477},{"column":48,"numberValue":601.96509474798376},{"column":49,"numberValue":438.62935777813229},{"column":50,"numberValue":346.62497802379436},{"column":51,"numberValue":357.07359232242058},{"column":52,"numberValue":367.52220662104376},{"column":53,"numberValue":377.97082091966695},{"column":54,"numberValue":388.41943521829007},{"column":55,"numberValue":398.86804951691332},{"column":56,"numberValue":409.31666381553948},{"column":57,"numberValue":398.18851977101959},{"column":58,"numberValue":387.06037572650268},{"column":59,"numberValue":375.93223168198589},{"column":60,"numberValue":364.80408763746903},{"column":61,"numberValue":353.67594359295247}],"excludeFromChart":true}]},{"id":49,"name":"Romania","rows":[{"id":10189,"name":"4.C.2.e  Other Land Converted to Grassland","unitId":140,"cells":[{"column":0,"numberValue":-23.64142000000002},{"column":32,"numberValue":-24.77075333333336},{"column":33,"numberValue":-24.76994666666669},{"column":34,"numberValue":-24.76914000000002},{"column":35,"numberValue":-24.76833333333336},{"column":36,"numberValue":-24.76833333333336},{"column":37,"numberValue":-24.76833333333336},{"column":38,"numberValue":-24.76833333333336},{"column":39,"numberValue":-24.76833333333336},{"column":40,"numberValue":-24.76833333333336},{"column":41,"numberValue":-24.76833333333336},{"column":42,"numberValue":-24.76833333333336},{"column":43,"numberValue":-24.76833333333336},{"column":44,"numberValue":-24.76833333333336},{"column":45,"numberValue":-24.76833333333336},{"column":46,"numberValue":-24.76833333333336},{"column":47,"numberValue":-24.76833333333336},{"column":48,"numberValue":-24.76833333333336},{"column":49,"numberValue":-24.76833333333336},{"column":50,"numberValue":-24.76833333333336},{"column":51,"numberValue":-24.76833333333336},{"column":52,"numberValue":-24.76833333333336},{"column":53,"numberValue":-24.76833333333336},{"column":54,"numberValue":-31.00349881612301},{"column":55,"numberValue":-32.19414144444233},{"column":56,"numberValue":-26.24046963821667},{"column":57,"numberValue":-24.64995766209488},{"column":58,"numberValue":-23.65511667060203},{"column":59,"numberValue":-22.65292563674054},{"column":60,"numberValue":-21.92576925147780},{"column":61,"numberValue":-21.26780507654658}],"excludeFromChart":true}]},{"id":50,"name":"Russian Federation","rows":[{"id":10189,"name":"4.C.2.e  Other Land Converted to Grassland","unitId":140,"cells":[{"column":0,"stringValue":"NO"},{"column":32,"stringValue":"NO"},{"column":33,"stringValue":"NO"},{"column":34,"stringValue":"NO"},{"column":35,"stringValue":"NO"},{"column":36,"stringValue":"NO"},{"column":37,"stringValue":"NO"},{"column":38,"stringValue":"NO"},{"column":39,"stringValue":"NO"},{"column":40,"stringValue":"NO"},{"column":41,"stringValue":"NO"},{"column":42,"stringValue":"NO"},{"column":43,"stringValue":"NO"},{"column":44,"stringValue":"NO"},{"column":45,"stringValue":"NO"},{"column":46,"stringValue":"NO"},{"column":47,"stringValue":"NO"},{"column":48,"stringValue":"NO"},{"column":49,"stringValue":"NO"},{"column":50,"stringValue":"NO"},{"column":51,"stringValue":"NO"},{"column":52,"numberValue":-2911.92430119237680},{"column":53,"numberValue":-17584.51480676937000},{"column":54,"numberValue":-24631.12318295226900},{"column":55,"stringValue":"NO"},{"column":56,"numberValue":-59465.82399926926200},{"column":57,"numberValue":-23604.88294547750000},{"column":58,"numberValue":-38563.54001485098700},{"column":59,"numberValue":-41766.76707743706400},{"column":60,"numberValue":-39257.41033058276700},{"column":61,"stringValue":"NO"}],"excludeFromChart":true}]},{"id":51,"name":"Slovakia","rows":[{"id":10189,"name":"4.C.2.e  Other Land Converted to Grassland","unitId":140,"cells":[{"column":0,"numberValue":-16.60288666666668},{"column":32,"numberValue":-16.60288666666668},{"column":33,"numberValue":-16.60288666666668},{"column":34,"numberValue":-19.44611166666668},{"column":35,"numberValue":-16.59901833333335},{"column":36,"numberValue":-16.19284333333335},{"column":37,"numberValue":-17.13284833333335},{"column":38,"numberValue":-17.44618333333335},{"column":39,"numberValue":-19.63179166666668},{"column":40,"numberValue":-19.63179166666668},{"column":41,"numberValue":-11.39997833333334},{"column":42,"numberValue":-9.45033833333334},{"column":43,"numberValue":-9.45033833333334},{"column":44,"numberValue":-9.45033833333334},{"column":45,"numberValue":-6.55682500000001},{"column":46,"numberValue":-6.55682500000001},{"column":47,"numberValue":-6.55682500000001},{"column":48,"numberValue":-6.55682500000001},{"column":49,"numberValue":-6.55682500000001},{"column":50,"numberValue":-6.55682500000001},{"column":51,"numberValue":-6.55682500000001},{"column":52,"numberValue":-6.55682500000001},{"column":53,"numberValue":-6.55682500000001},{"column":54,"numberValue":-3.57820833333334},{"column":55,"numberValue":-3.57820833333334},{"column":56,"numberValue":-3.57820833333334},{"column":57,"numberValue":-2.63820333333334},{"column":58,"numberValue":-2.18560833333334},{"column":59,"numberValue":0E-14},{"column":60,"numberValue":0E-14},{"column":61,"numberValue":0E-14}],"excludeFromChart":true}]},{"id":52,"name":"Slovenia","rows":[{"id":10189,"name":"4.C.2.e  Other Land Converted to Grassland","unitId":140,"cells":[{"column":0,"numberValue":-224.55758498678776},{"column":32,"numberValue":-234.00575998678775},{"column":33,"numberValue":-228.94749875634972},{"column":34,"numberValue":-199.52377919257839},{"column":35,"numberValue":-188.99640962880704},{"column":36,"numberValue":-213.97660006503577},{"column":37,"numberValue":-201.07620050126448},{"column":38,"numberValue":-190.49870449690957},{"column":39,"numberValue":-191.91340084493561},{"column":40,"numberValue":-185.21672909296160},{"column":41,"numberValue":-176.60053974098756},{"column":42,"numberValue":-161.99573505091840},{"column":43,"numberValue":-156.02875956084927},{"column":44,"numberValue":-158.43004208506574},{"column":45,"numberValue":-137.45247011546584},{"column":46,"numberValue":-138.47368149348495},{"column":47,"numberValue":-126.45787620483743},{"column":48,"numberValue":-109.44259474952317},{"column":49,"numberValue":-98.34312766685042},{"column":50,"numberValue":-86.65772725084439},{"column":51,"numberValue":-74.17692233483832},{"column":52,"numberValue":-60.71174941883229},{"column":53,"numberValue":-56.97854156659755},{"column":54,"numberValue":-52.55539721436276},{"column":55,"numberValue":-48.85734536212806},{"column":56,"numberValue":-46.75156734322665},{"column":57,"numberValue":-43.38749749099191},{"column":58,"numberValue":-37.26875454124551},{"column":59,"numberValue":-30.34937554388009},{"column":60,"numberValue":-24.82075116556228},{"column":61,"numberValue":-18.65283166819693}],"excludeFromChart":true}]},{"id":17,"name":"Spain","rows":[{"id":10189,"name":"4.C.2.e  Other Land Converted to Grassland","unitId":140,"cells":[{"column":0,"numberValue":-177.07308856013847},{"column":32,"numberValue":-177.07308856013847},{"column":33,"numberValue":-167.04406704830151},{"column":34,"numberValue":-164.07549565009523},{"column":35,"numberValue":-150.90300674919311},{"column":36,"numberValue":-150.90300674919311},{"column":37,"numberValue":-126.55693342120600},{"column":38,"numberValue":-119.48848917592642},{"column":39,"numberValue":-108.00835222769273},{"column":40,"numberValue":-66.79771354330872},{"column":41,"numberValue":-36.66331902695007},{"column":42,"stringValue":"NO"},{"column":43,"stringValue":"NO"},{"column":44,"stringValue":"NO"},{"column":45,"stringValue":"NO"},{"column":46,"stringValue":"NO"},{"column":47,"stringValue":"NO"},{"column":48,"stringValue":"NO"},{"column":49,"stringValue":"NO"},{"column":50,"stringValue":"NO"},{"column":51,"stringValue":"NO"},{"column":52,"stringValue":"NO"},{"column":53,"stringValue":"NO"},{"column":54,"stringValue":"NO"},{"column":55,"stringValue":"NO"},{"column":56,"stringValue":"NO"},{"column":57,"stringValue":"NO"},{"column":58,"stringValue":"NO"},{"column":59,"stringValue":"NO"},{"column":60,"stringValue":"NO"},{"column":61,"stringValue":"NO"}],"excludeFromChart":true}]},{"id":53,"name":"Sweden","rows":[{"id":10189,"name":"4.C.2.e  Other Land Converted to Grassland","unitId":140,"cells":[{"column":0,"stringValue":"NO"},{"column":32,"stringValue":"NO"},{"column":33,"stringValue":"NO"},{"column":34,"stringValue":"NO"},{"column":35,"stringValue":"NO"},{"column":36,"stringValue":"NO"},{"column":37,"stringValue":"NO"},{"column":38,"stringValue":"NO"},{"column":39,"stringValue":"NO"},{"column":40,"stringValue":"NO"},{"column":41,"stringValue":"NO"},{"column":42,"stringValue":"NO"},{"column":43,"stringValue":"NO"},{"column":44,"numberValue":-9.34318366666668},{"column":45,"numberValue":-9.34253833333334},{"column":46,"numberValue":-7.85252600000001},{"column":47,"numberValue":-7.84998133333334},{"column":48,"numberValue":-7.85693700000001},{"column":49,"numberValue":-24.37513100000002},{"column":50,"numberValue":-24.27096466666669},{"column":51,"numberValue":-14.81731900000001},{"column":52,"numberValue":-14.84132833333335},{"column":53,"numberValue":-14.84896600000001},{"column":54,"numberValue":-14.87774933333335},{"column":55,"numberValue":-14.93538200000001},{"column":56,"numberValue":-10.99712166666668},{"column":57,"numberValue":-10.99480066666668},{"column":58,"numberValue":-11.01048666666668},{"column":59,"numberValue":-10.98395833333334},{"column":60,"numberValue":-10.99619400000001},{"column":61,"numberValue":-11.03191466666668}],"excludeFromChart":true}]},{"id":10,"name":"Switzerland","rows":[{"id":10189,"name":"4.C.2.e  Other Land Converted to Grassland","unitId":140,"cells":[{"column":0,"numberValue":-95.15567774900008},{"column":32,"numberValue":-95.15567774900008},{"column":33,"numberValue":-95.16662949566675},{"column":34,"numberValue":-95.18532782000008},{"column":35,"numberValue":-96.99744004133342},{"column":36,"numberValue":-98.60624512933342},{"column":37,"numberValue":-99.57077245500008},{"column":38,"numberValue":-101.36146567800007},{"column":39,"numberValue":-102.49752568000008},{"column":40,"numberValue":-102.64805241900008},{"column":41,"numberValue":-103.67276474133344},{"column":42,"numberValue":-104.28273337166677},{"column":43,"numberValue":-104.89501946733344},{"column":44,"numberValue":-105.50383778733344},{"column":45,"numberValue":-106.11440296966676},{"column":46,"numberValue":-106.73017733033343},{"column":47,"numberValue":-105.94462890366675},{"column":48,"numberValue":-108.94694221400010},{"column":49,"numberValue":-117.42964072400012},{"column":50,"numberValue":-134.27443580466681},{"column":51,"numberValue":-136.40453265633346},{"column":52,"numberValue":-136.90162024733345},{"column":53,"numberValue":-140.16978673133346},{"column":54,"numberValue":-143.43513113600011},{"column":55,"numberValue":-146.20721237833348},{"column":56,"numberValue":-157.73767748200015},{"column":57,"numberValue":-158.43370131600014},{"column":58,"numberValue":-157.50825286166679},{"column":59,"numberValue":-158.88858383200014},{"column":60,"numberValue":-160.87714864833347},{"column":61,"numberValue":-162.80795069366681}],"excludeFromChart":true}]},{"id":54,"name":"Turkey","rows":[{"id":10189,"name":"4.C.2.e  Other Land Converted to Grassland","unitId":140,"cells":[{"column":0,"stringValue":"NO"},{"column":32,"stringValue":"NO"},{"column":33,"numberValue":-2.65518960300000},{"column":34,"numberValue":-7.36347367800001},{"column":35,"numberValue":-6.78514958550001},{"column":36,"numberValue":-8.53362511650001},{"column":37,"numberValue":-9.69409786950001},{"column":38,"numberValue":-11.73285738900001},{"column":39,"numberValue":-11.04420334050001},{"column":40,"numberValue":-13.34883696300001},{"column":41,"numberValue":-13.54007160000001},{"column":42,"numberValue":-13.45203946350001},{"column":43,"numberValue":-15.93514929600001},{"column":44,"numberValue":-20.40437653650002},{"column":45,"numberValue":-20.62206243900002},{"column":46,"numberValue":-25.89557978700002},{"column":47,"numberValue":-26.63446722750002},{"column":48,"numberValue":-32.22431977050003},{"column":49,"numberValue":-34.21213186050003},{"column":50,"numberValue":-37.32172735500003},{"column":51,"numberValue":-39.06352226700004},{"column":52,"numberValue":-43.78102705350004},{"column":53,"numberValue":-41.99226292800004},{"column":54,"numberValue":-41.28347445750004},{"column":55,"numberValue":-39.75927050700004},{"column":56,"numberValue":-40.56685761150004},{"column":57,"numberValue":-39.54604034700004},{"column":58,"numberValue":-39.83070599447394},{"column":59,"numberValue":-40.50102066795715},{"column":60,"numberValue":-40.26928558461941},{"column":61,"numberValue":-40.82472248433337}],"excludeFromChart":true}]},{"id":55,"name":"Ukraine","rows":[{"id":10189,"name":"4.C.2.e  Other Land Converted to Grassland","unitId":140,"cells":[{"column":0,"stringValue":"NO"},{"column":32,"stringValue":"NO"},{"column":33,"numberValue":-171.00926856405778},{"column":34,"numberValue":-171.00926856405778},{"column":35,"numberValue":-918.38741939052932},{"column":36,"numberValue":-985.34836368991614},{"column":37,"numberValue":-985.34836368991614},{"column":38,"numberValue":-1124.64477319512660},{"column":39,"numberValue":-1265.16824541734810},{"column":40,"numberValue":-1450.50705020673920},{"column":41,"numberValue":-1690.32654254389600},{"column":42,"numberValue":-1690.32654254389600},{"column":43,"numberValue":-1690.32654254389600},{"column":44,"numberValue":-1735.40275876012310},{"column":45,"numberValue":-1761.17942542678820},{"column":46,"numberValue":-1761.17942542678820},{"column":47,"numberValue":-1761.17942542678820},{"column":48,"numberValue":-1761.17942542678820},{"column":49,"numberValue":-1761.17942542678820},{"column":50,"numberValue":-1761.17942542678820},{"column":51,"numberValue":-1761.17942542678820},{"column":52,"numberValue":-1761.17942542678820},{"column":53,"numberValue":-1590.17015686273020},{"column":54,"numberValue":-1590.17015686273020},{"column":55,"numberValue":-842.79200603625861},{"column":56,"numberValue":-775.83106173687167},{"column":57,"numberValue":-775.83106173687167},{"column":58,"numberValue":-636.53465223166131},{"column":59,"numberValue":-496.01118000943984},{"column":60,"numberValue":-310.67237522004859},{"column":61,"numberValue":-70.85288288289225}],"excludeFromChart":true}]},{"id":27,"name":"United Kingdom of Great Britain and Northern Ireland","rows":[{"id":10189,"name":"4.C.2.e  Other Land Converted to Grassland","unitId":140,"cells":[{"column":0,"stringValue":"NO"},{"column":32,"stringValue":"NO"},{"column":33,"stringValue":"NO"},{"column":34,"stringValue":"NO"},{"column":35,"stringValue":"NO"},{"column":36,"stringValue":"NO"},{"column":37,"stringValue":"NO"},{"column":38,"stringValue":"NO"},{"column":39,"stringValue":"NO"},{"column":40,"stringValue":"NO"},{"column":41,"stringValue":"NO"},{"column":42,"stringValue":"NO"},{"column":43,"stringValue":"NO"},{"column":44,"stringValue":"NO"},{"column":45,"stringValue":"NO"},{"column":46,"stringValue":"NO"},{"column":47,"stringValue":"NO"},{"column":48,"stringValue":"NO"},{"column":49,"stringValue":"NO"},{"column":50,"stringValue":"NO"},{"column":51,"stringValue":"NO"},{"column":52,"stringValue":"NO"},{"column":53,"stringValue":"NO"},{"column":54,"stringValue":"NO"},{"column":55,"stringValue":"NO"},{"column":56,"stringValue":"NO"},{"column":57,"stringValue":"NO"},{"column":58,"stringValue":"NO"},{"column":59,"stringValue":"NO"},{"column":60,"stringValue":"NO"},{"column":61,"stringValue":"NO"}],"excludeFromChart":true}]},{"id":56,"name":"United States of America","rows":[{"id":10189,"name":"4.C.2.e  Other Land Converted to Grassland","unitId":140,"cells":[{"column":0,"numberValue":-4191.81244106120360},{"column":32,"numberValue":-4191.81244106120360},{"column":33,"numberValue":-4268.62299442590300},{"column":34,"numberValue":-4471.62044048590360},{"column":35,"numberValue":-7210.62202146540680},{"column":36,"numberValue":-11404.89115814351000},{"column":37,"numberValue":-13950.61103231181400},{"column":38,"numberValue":-16718.02381403181400},{"column":39,"numberValue":-18788.27011317181300},{"column":40,"numberValue":-21393.41040536651800},{"column":41,"numberValue":-24707.55945887152100},{"column":42,"numberValue":-28321.05719297151900},{"column":43,"numberValue":-31422.01643359382400},{"column":44,"numberValue":-31413.86100824382100},{"column":45,"numberValue":-31542.15444304383300},{"column":46,"numberValue":-31495.83924984382600},{"column":47,"numberValue":-31690.64630244382700},{"column":48,"numberValue":-31622.05907874383400},{"column":49,"numberValue":-31695.10599850482300},{"column":50,"numberValue":-31705.63540329942400},{"column":51,"numberValue":-31792.51529249943600},{"column":52,"numberValue":-31742.93058579942200},{"column":53,"numberValue":-31989.22434447632300},{"column":54,"numberValue":-31957.76707927632700},{"column":55,"numberValue":-29365.17256991791500},{"column":56,"numberValue":-25468.57343611792400},{"column":57,"numberValue":-22848.59429298792000},{"column":58,"numberValue":-18310.72318214420700},{"column":59,"numberValue":-18345.19933463214700},{"column":60,"numberValue":-18090.01309361118900},{"column":61,"numberValue":-17617.25039892898000}],"excludeFromChart":true}]}],"generated":"Saturday, 5 February 2022 01:11:46 CET"}