{"columns":[{"id":32,"name":"1990"},{"id":33,"name":"1991"},{"id":34,"name":"1992"},{"id":35,"name":"1993"},{"id":36,"name":"1994"},{"id":37,"name":"1995"},{"id":38,"name":"1996"},{"id":39,"name":"1997"},{"id":40,"name":"1998"},{"id":41,"name":"1999"},{"id":42,"name":"2000"},{"id":43,"name":"2001"},{"id":44,"name":"2002"},{"id":45,"name":"2003"},{"id":46,"name":"2004"},{"id":47,"name":"2005"},{"id":48,"name":"2006"},{"id":49,"name":"2007"},{"id":50,"name":"2008"},{"id":51,"name":"2009"},{"id":52,"name":"2010"},{"id":53,"name":"2011"},{"id":54,"name":"2012"},{"id":55,"name":"2013"},{"id":56,"name":"2014"},{"id":57,"name":"2015"},{"id":58,"name":"2016"},{"id":59,"name":"2017"},{"id":60,"name":"2018"},{"id":61,"name":"Last Inventory Year (2019)"}],"data":[{"id":100064,"name":"Afghanistan","rows":[{"id":14435,"name":"1.A.3  Transport","unitId":17,"cells":[{"column":47,"numberValue":1690.79000000000000},{"column":55,"numberValue":5255.00000000000000}],"excludeFromChart":true}]},{"id":100065,"name":"Albania","rows":[{"id":14435,"name":"1.A.3  Transport","unitId":17,"cells":[{"column":42,"numberValue":1817.61000000000000},{"column":43,"numberValue":1835.36000000000000},{"column":44,"numberValue":1906.07000000000000},{"column":45,"numberValue":1996.71000000000000},{"column":46,"numberValue":2115.09000000000000},{"column":47,"numberValue":2085.95000000000000},{"column":48,"numberValue":2103.11000000000000},{"column":49,"numberValue":2124.57000000000000},{"column":50,"numberValue":2150.31000000000000},{"column":51,"numberValue":2306.46000000000000}],"excludeFromChart":true}]},{"id":100066,"name":"Algeria","rows":[{"id":14435,"name":"1.A.3  Transport","unitId":17,"cells":[{"column":36,"numberValue":13953.00000000000000},{"column":42,"numberValue":12789.98000000000000}],"excludeFromChart":true}]},{"id":100067,"name":"Andorra","rows":[{"id":14435,"name":"1.A.3  Transport","unitId":null,"cells":[],"excludeFromChart":true}]},{"id":100068,"name":"Angola","rows":[{"id":14435,"name":"1.A.3  Transport","unitId":null,"cells":[],"excludeFromChart":true}]},{"id":100069,"name":"Antigua and Barbuda","rows":[{"id":14435,"name":"1.A.3  Transport","unitId":17,"cells":[{"column":32,"numberValue":83.67000000000000},{"column":42,"numberValue":182.63000000000000}],"excludeFromChart":true}]},{"id":100070,"name":"Argentina","rows":[{"id":14435,"name":"1.A.3  Transport","unitId":17,"cells":[{"column":32,"numberValue":27858.83271605100000},{"column":36,"numberValue":35658.17687575860000},{"column":39,"numberValue":40844.22703778720000},{"column":42,"numberValue":40237.55623675210000},{"column":52,"numberValue":53652.03000000000000},{"column":54,"numberValue":54640.69000000000000}],"excludeFromChart":true}]},{"id":100071,"name":"Armenia","rows":[{"id":14435,"name":"1.A.3  Transport","unitId":17,"cells":[{"column":32,"numberValue":3783.01700000000000},{"column":42,"numberValue":658.31100000000000},{"column":48,"numberValue":970.57900000000000},{"column":52,"numberValue":1247.74500000000000}],"excludeFromChart":true}]},{"id":100072,"name":"Azerbaijan","rows":[{"id":14435,"name":"1.A.3  Transport","unitId":17,"cells":[{"column":32,"numberValue":5394.00000000000000},{"column":33,"numberValue":4701.74000000000000},{"column":34,"numberValue":3943.90000000000000},{"column":35,"numberValue":3638.13000000000000},{"column":36,"numberValue":3182.68000000000000},{"column":37,"numberValue":2843.22000000000000},{"column":38,"numberValue":2638.81000000000000},{"column":39,"numberValue":2446.86000000000000},{"column":40,"numberValue":2218.49000000000000},{"column":41,"numberValue":1362.23000000000000},{"column":42,"numberValue":2119.00000000000000},{"column":43,"numberValue":2330.17000000000000},{"column":44,"numberValue":2715.16000000000000},{"column":45,"numberValue":2952.43000000000000},{"column":46,"numberValue":3734.26000000000000},{"column":47,"numberValue":4158.00000000000000},{"column":48,"numberValue":4727.00000000000000},{"column":49,"numberValue":3729.00000000000000},{"column":50,"numberValue":4686.00000000000000},{"column":51,"numberValue":4165.00000000000000},{"column":52,"numberValue":4861.00000000000000},{"column":53,"numberValue":5057.00000000000000},{"column":54,"numberValue":5223.00000000000000},{"column":55,"numberValue":7413.32250700000000}],"excludeFromChart":true}]},{"id":100073,"name":"Bahamas","rows":[{"id":14435,"name":"1.A.3  Transport","unitId":null,"cells":[],"excludeFromChart":true}]},{"id":100074,"name":"Bahrain","rows":[{"id":14435,"name":"1.A.3  Transport","unitId":17,"cells":[{"column":36,"numberValue":1300.40000000000000},{"column":42,"numberValue":1519.00000000000000}],"excludeFromChart":true}]},{"id":100075,"name":"Bangladesh","rows":[{"id":14435,"name":"1.A.3  Transport","unitId":17,"cells":[{"column":36,"numberValue":2538.12000000000000},{"column":43,"numberValue":4551.00000000000000},{"column":47,"numberValue":5500.00000000000000}],"excludeFromChart":true}]},{"id":100076,"name":"Barbados","rows":[{"id":14435,"name":"1.A.3  Transport","unitId":17,"cells":[{"column":32,"numberValue":225.12000000000000},{"column":36,"numberValue":257.44000000000000},{"column":39,"numberValue":251.66000000000000},{"column":42,"numberValue":362.00000000000000},{"column":43,"numberValue":265.00000000000000},{"column":44,"numberValue":371.00000000000000},{"column":45,"numberValue":380.00000000000000},{"column":46,"numberValue":392.00000000000000},{"column":47,"numberValue":406.00000000000000},{"column":48,"numberValue":413.00000000000000},{"column":49,"numberValue":424.00000000000000},{"column":50,"numberValue":436.00000000000000},{"column":51,"numberValue":443.00000000000000},{"column":52,"numberValue":449.00000000000000}],"excludeFromChart":true}]},{"id":100077,"name":"Belize","rows":[{"id":14435,"name":"1.A.3  Transport","unitId":17,"cells":[{"column":36,"numberValue":313.90100000000000}],"excludeFromChart":true}]},{"id":100078,"name":"Benin","rows":[{"id":14435,"name":"1.A.3  Transport","unitId":17,"cells":[{"column":37,"numberValue":399.80400000000000},{"column":42,"numberValue":908.07000000000000}],"excludeFromChart":true}]},{"id":100079,"name":"Bhutan","rows":[{"id":14435,"name":"1.A.3  Transport","unitId":17,"cells":[{"column":36,"numberValue":43.20000000000000},{"column":42,"numberValue":118.11000000000000},{"column":57,"numberValue":424.70000000000000}],"excludeFromChart":true}]},{"id":100080,"name":"Bolivia (Plurinational State of)","rows":[{"id":14435,"name":"1.A.3  Transport","unitId":17,"cells":[{"column":32,"numberValue":2088.49000000000000},{"column":36,"numberValue":2503.36000000000000},{"column":40,"numberValue":3655.93000000000000},{"column":42,"numberValue":3194.77000000000000},{"column":44,"numberValue":4040.09000000000000},{"column":46,"numberValue":4274.55000000000000}],"excludeFromChart":true}]},{"id":100081,"name":"Bosnia and Herzegovina","rows":[{"id":14435,"name":"1.A.3  Transport","unitId":17,"cells":[{"column":32,"numberValue":2357.65000000000000},{"column":44,"numberValue":1954.54000000000000},{"column":45,"numberValue":2046.18000000000000},{"column":46,"numberValue":2245.13000000000000},{"column":47,"numberValue":2222.35000000000000},{"column":48,"numberValue":2339.83000000000000},{"column":49,"numberValue":2372.17000000000000},{"column":50,"numberValue":2497.32000000000000},{"column":51,"numberValue":2529.91000000000000},{"column":52,"numberValue":2579.46000000000000},{"column":53,"numberValue":2666.19000000000000},{"column":54,"numberValue":2753.18000000000000},{"column":55,"numberValue":2881.00000000000000},{"column":56,"numberValue":3037.00000000000000}],"excludeFromChart":true}]},{"id":100082,"name":"Botswana","rows":[{"id":14435,"name":"1.A.3  Transport","unitId":17,"cells":[{"column":36,"numberValue":801.19100000000000},{"column":42,"numberValue":490.00000000000000},{"column":57,"numberValue":1985.09651700000000}],"excludeFromChart":true}]},{"id":100083,"name":"Brazil","rows":[{"id":14435,"name":"1.A.3  Transport","unitId":17,"cells":[{"column":32,"numberValue":80584.20000000000000},{"column":33,"numberValue":84697.70000000000000},{"column":34,"numberValue":84994.50000000000000},{"column":35,"numberValue":88222.70000000000000},{"column":36,"numberValue":92699.70000000000000},{"column":37,"numberValue":102100.00000000000000},{"column":38,"numberValue":109739.50000000000000},{"column":39,"numberValue":116582.30000000000000},{"column":40,"numberValue":123689.20000000000000},{"column":41,"numberValue":122576.10000000000000},{"column":42,"numberValue":124184.60000000000000},{"column":43,"numberValue":127440.00000000000000},{"column":44,"numberValue":130853.10000000000000},{"column":45,"numberValue":129976.40000000000000},{"column":46,"numberValue":138324.80000000000000},{"column":47,"numberValue":139224.30000000000000},{"column":48,"numberValue":143943.30000000000000},{"column":49,"numberValue":149970.50000000000000},{"column":50,"numberValue":155753.60000000000000},{"column":51,"numberValue":154233.10000000000000},{"column":52,"numberValue":172857.40000000000000},{"column":53,"numberValue":189394.60000000000000},{"column":54,"numberValue":206549.50000000000000},{"column":55,"numberValue":213387.60000000000000},{"column":56,"numberValue":219076.40000000000000},{"column":57,"numberValue":204049.50000000000000},{"column":58,"numberValue":205546.90000000000000}],"excludeFromChart":true}]},{"id":100084,"name":"Brunei Darussalam","rows":[{"id":14435,"name":"1.A.3  Transport","unitId":17,"cells":[{"column":52,"numberValue":1171.40000000000000}],"excludeFromChart":true}]},{"id":100085,"name":"Burkina Faso","rows":[{"id":14435,"name":"1.A.3  Transport","unitId":17,"cells":[{"column":36,"numberValue":323.81899876370000},{"column":49,"numberValue":776.40000000000000}],"excludeFromChart":true}]},{"id":100086,"name":"Burundi","rows":[{"id":14435,"name":"1.A.3  Transport","unitId":17,"cells":[{"column":40,"numberValue":90.78975600000000},{"column":47,"numberValue":75.79524500000000},{"column":52,"numberValue":82.92632600000000},{"column":57,"numberValue":71.35667900000000}],"excludeFromChart":true}]},{"id":100087,"name":"Cabo Verde","rows":[{"id":14435,"name":"1.A.3  Transport","unitId":17,"cells":[{"column":37,"numberValue":1.84742900000000},{"column":42,"numberValue":137.55100000000000}],"excludeFromChart":true}]},{"id":100088,"name":"Cambodia","rows":[{"id":14435,"name":"1.A.3  Transport","unitId":17,"cells":[{"column":36,"numberValue":831.29000000000000},{"column":42,"numberValue":710.17000000000000}],"excludeFromChart":true}]},{"id":100089,"name":"Cameroon","rows":[{"id":14435,"name":"1.A.3  Transport","unitId":17,"cells":[{"column":36,"numberValue":1352.36000000000000},{"column":42,"numberValue":1777.00000000000000}],"excludeFromChart":true}]},{"id":100090,"name":"Central African Republic","rows":[{"id":14435,"name":"1.A.3  Transport","unitId":17,"cells":[{"column":36,"numberValue":122.00000000000000},{"column":45,"numberValue":58.66000000000000},{"column":46,"numberValue":69.04000000000000},{"column":47,"numberValue":82.49000000000000},{"column":48,"numberValue":80.97000000000000},{"column":49,"numberValue":100.42000000000000},{"column":50,"numberValue":99.39000000000000},{"column":51,"numberValue":117.15000000000000},{"column":52,"numberValue":140.82000000000000}],"excludeFromChart":true}]},{"id":100091,"name":"Chad","rows":[{"id":14435,"name":"1.A.3  Transport","unitId":null,"cells":[],"excludeFromChart":true}]},{"id":100092,"name":"Chile","rows":[{"id":14435,"name":"1.A.3  Transport","unitId":17,"cells":[{"column":32,"numberValue":9080.90000000000000},{"column":35,"numberValue":12254.20000000000000},{"column":36,"numberValue":12376.20000000000000},{"column":42,"numberValue":17173.50000000000000},{"column":48,"numberValue":17075.87215431140000},{"column":52,"numberValue":20516.30000000000000},{"column":55,"numberValue":24346.00000000000000},{"column":58,"numberValue":26393.10000000000000},{"column":60,"numberValue":28630.70000000000000}],"excludeFromChart":true}]},{"id":100093,"name":"China","rows":[{"id":14435,"name":"1.A.3  Transport","unitId":17,"cells":[{"column":36,"numberValue":165567.00000000000000},{"column":52,"numberValue":660868.00000000000000},{"column":54,"numberValue":797083.00000000000000},{"column":56,"numberValue":827909.00000000000000}],"excludeFromChart":true}]},{"id":100094,"name":"Colombia","rows":[{"id":14435,"name":"1.A.3  Transport","unitId":17,"cells":[{"column":32,"numberValue":14607.16000000000000},{"column":36,"numberValue":19220.76000000000000},{"column":42,"numberValue":19987.16000000000000},{"column":46,"numberValue":21768.68000000000000}],"excludeFromChart":true}]},{"id":100095,"name":"Comoros","rows":[{"id":14435,"name":"1.A.3  Transport","unitId":17,"cells":[{"column":42,"numberValue":44.71704500000000}],"excludeFromChart":true}]},{"id":100096,"name":"Congo","rows":[{"id":14435,"name":"1.A.3  Transport","unitId":17,"cells":[{"column":36,"numberValue":370.24000000000000},{"column":42,"numberValue":385.65000000000000}],"excludeFromChart":true}]},{"id":100097,"name":"Cook Islands","rows":[{"id":14435,"name":"1.A.3  Transport","unitId":17,"cells":[{"column":36,"numberValue":16.05235000000000}],"excludeFromChart":true}]},{"id":100098,"name":"Costa Rica","rows":[{"id":14435,"name":"1.A.3  Transport","unitId":17,"cells":[{"column":42,"numberValue":3153.22000000000000},{"column":47,"numberValue":3890.90000000000000}],"excludeFromChart":true}]},{"id":100099,"name":"Cote d'Ivoire","rows":[{"id":14435,"name":"1.A.3  Transport","unitId":17,"cells":[{"column":42,"numberValue":2202.74000000000000}],"excludeFromChart":true}]},{"id":100100,"name":"Cuba","rows":[{"id":14435,"name":"1.A.3  Transport","unitId":17,"cells":[{"column":32,"numberValue":1980.72000000000000},{"column":42,"numberValue":993.76000000000000},{"column":44,"numberValue":917.73000000000000}],"excludeFromChart":true}]},{"id":100101,"name":"Democratic People's Republic of Korea","rows":[{"id":14435,"name":"1.A.3  Transport","unitId":17,"cells":[{"column":32,"numberValue":7180.00000000000000},{"column":36,"numberValue":4576.00000000000000},{"column":42,"numberValue":1414.00000000000000},{"column":44,"numberValue":1488.00000000000000}],"excludeFromChart":true}]},{"id":100102,"name":"Democratic Republic of the Congo","rows":[{"id":14435,"name":"1.A.3  Transport","unitId":17,"cells":[{"column":36,"numberValue":1044.13800000000000},{"column":41,"numberValue":808.00000000000000},{"column":42,"numberValue":1030.03000000000000},{"column":43,"numberValue":830.00000000000000},{"column":44,"numberValue":827.00000000000000},{"column":45,"numberValue":833.00000000000000}],"excludeFromChart":true}]},{"id":100103,"name":"Djibouti","rows":[{"id":14435,"name":"1.A.3  Transport","unitId":17,"cells":[{"column":36,"numberValue":125.53000000000000},{"column":42,"numberValue":108.75000000000000}],"excludeFromChart":true}]},{"id":100104,"name":"Dominica","rows":[{"id":14435,"name":"1.A.3  Transport","unitId":17,"cells":[{"column":36,"numberValue":37.98992850000000},{"column":42,"numberValue":47.13520000000000},{"column":43,"numberValue":53.70000000000000},{"column":44,"numberValue":55.40000000000000},{"column":45,"numberValue":46.80000000000000},{"column":46,"numberValue":42.90000000000000},{"column":47,"numberValue":46.80000000000000},{"column":48,"numberValue":51.24000000000000},{"column":49,"numberValue":53.95000000000000},{"column":50,"numberValue":51.43000000000000},{"column":51,"numberValue":54.85000000000000},{"column":52,"numberValue":56.62000000000000},{"column":53,"numberValue":59.92000000000000},{"column":54,"numberValue":60.38000000000000},{"column":55,"numberValue":64.41000000000000},{"column":56,"numberValue":70.24000000000000},{"column":57,"numberValue":69.76000000000000},{"column":58,"numberValue":71.33000000000000},{"column":59,"numberValue":67.17000000000000}],"excludeFromChart":true}]},{"id":100105,"name":"Dominican Republic","rows":[{"id":14435,"name":"1.A.3  Transport","unitId":17,"cells":[{"column":32,"numberValue":2430.43000000000000},{"column":36,"numberValue":4617.23000000000000},{"column":40,"numberValue":4781.20000000000000},{"column":42,"numberValue":6183.28000000000000},{"column":52,"numberValue":5460.36610000000000}],"excludeFromChart":true}]},{"id":100106,"name":"Ecuador","rows":[{"id":14435,"name":"1.A.3  Transport","unitId":17,"cells":[{"column":32,"numberValue":7158.08000000000000},{"column":52,"numberValue":15163.15288792350000},{"column":54,"numberValue":16977.11400000000000}],"excludeFromChart":true}]},{"id":100107,"name":"Egypt","rows":[{"id":14435,"name":"1.A.3  Transport","unitId":17,"cells":[{"column":32,"numberValue":21161.93000000000000},{"column":42,"numberValue":27209.82000000000000},{"column":47,"numberValue":33091.48300000000000}],"excludeFromChart":true}]},{"id":100108,"name":"El Salvador","rows":[{"id":14435,"name":"1.A.3  Transport","unitId":17,"cells":[{"column":36,"numberValue":1821.86000000000000},{"column":47,"numberValue":2483.31000000000000}],"excludeFromChart":true}]},{"id":100109,"name":"Equatorial Guinea","rows":[{"id":14435,"name":"1.A.3  Transport","unitId":null,"cells":[],"excludeFromChart":true}]},{"id":100110,"name":"Eritrea","rows":[{"id":14435,"name":"1.A.3  Transport","unitId":17,"cells":[{"column":36,"numberValue":1212.90000000000000},{"column":37,"numberValue":326.29000000000000},{"column":38,"numberValue":365.12000000000000},{"column":39,"numberValue":354.39000000000000},{"column":40,"numberValue":222.07000000000000},{"column":41,"numberValue":203.33000000000000},{"column":42,"numberValue":199.00000000000000}],"excludeFromChart":true}]},{"id":100195,"name":"Eswatini","rows":[{"id":14435,"name":"1.A.3  Transport","unitId":17,"cells":[{"column":36,"numberValue":442.39880000000000}],"excludeFromChart":true}]},{"id":100111,"name":"Ethiopia","rows":[{"id":14435,"name":"1.A.3  Transport","unitId":17,"cells":[{"column":36,"numberValue":1033.99173160000000},{"column":37,"numberValue":820.00349450000000},{"column":38,"numberValue":1088.93703300000000},{"column":39,"numberValue":1473.45402500000000},{"column":40,"numberValue":1381.00499900000000},{"column":41,"numberValue":1419.54557200000000},{"column":42,"numberValue":1563.55527800000000},{"column":43,"numberValue":1949.61401300000000},{"column":44,"numberValue":2045.52072100000000},{"column":45,"numberValue":2133.15052700000000},{"column":46,"numberValue":2289.28886000000000},{"column":47,"numberValue":3192.45287000000000},{"column":48,"numberValue":3431.02285200000000},{"column":49,"numberValue":3756.42803000000000},{"column":50,"numberValue":3878.10362800000000},{"column":51,"numberValue":4041.13635600000000},{"column":52,"numberValue":6407.85670200000000},{"column":53,"numberValue":3769.76022800000000},{"column":54,"numberValue":3769.76022800000000},{"column":55,"numberValue":3918.22383300000000}],"excludeFromChart":true}]},{"id":100112,"name":"Fiji","rows":[{"id":14435,"name":"1.A.3  Transport","unitId":17,"cells":[{"column":36,"numberValue":528.00000000000000},{"column":46,"numberValue":733.01000000000000}],"excludeFromChart":true}]},{"id":100113,"name":"Gabon","rows":[{"id":14435,"name":"1.A.3  Transport","unitId":17,"cells":[{"column":36,"numberValue":551.00000000000000},{"column":42,"numberValue":404.69000000000000}],"excludeFromChart":true}]},{"id":100114,"name":"Gambia","rows":[{"id":14435,"name":"1.A.3  Transport","unitId":17,"cells":[{"column":35,"numberValue":109.08460000000000},{"column":42,"numberValue":99.75300000000000}],"excludeFromChart":true}]},{"id":100115,"name":"Georgia","rows":[{"id":14435,"name":"1.A.3  Transport","unitId":17,"cells":[{"column":32,"numberValue":3824.23000000000000},{"column":42,"numberValue":1120.46000000000000},{"column":43,"numberValue":1140.77000000000000},{"column":44,"numberValue":1201.29000000000000},{"column":45,"numberValue":1146.77000000000000},{"column":46,"numberValue":1211.19000000000000},{"column":47,"numberValue":1221.50000000000000},{"column":48,"numberValue":1758.87000000000000},{"column":49,"numberValue":2037.65000000000000},{"column":50,"numberValue":2184.07000000000000},{"column":51,"numberValue":2439.80400000000000},{"column":52,"numberValue":2573.86000000000000},{"column":53,"numberValue":2536.65000000000000},{"column":54,"numberValue":2655.07000000000000},{"column":55,"numberValue":3095.57000000000000},{"column":59,"numberValue":4144.59000000000000}],"excludeFromChart":true}]},{"id":100116,"name":"Ghana","rows":[{"id":14435,"name":"1.A.3  Transport","unitId":17,"cells":[{"column":32,"numberValue":1547.79600000000000},{"column":33,"numberValue":1157.38250000000000},{"column":34,"numberValue":1499.36000000000000},{"column":35,"numberValue":1652.31000000000000},{"column":36,"numberValue":1713.96000000000000},{"column":37,"numberValue":1864.00000000000000},{"column":38,"numberValue":2031.14000000000000},{"column":39,"numberValue":2089.64132600000000},{"column":40,"numberValue":2430.42749000000000},{"column":41,"numberValue":2765.34000000000000},{"column":42,"numberValue":2547.00000000000000},{"column":43,"numberValue":2555.81000000000000},{"column":44,"numberValue":1818.78000000000000},{"column":45,"numberValue":2616.75000000000000},{"column":46,"numberValue":3004.95000000000000},{"column":47,"numberValue":3029.67000000000000},{"column":48,"numberValue":3120.11000000000000}],"excludeFromChart":true}]},{"id":100117,"name":"Grenada","rows":[{"id":14435,"name":"1.A.3  Transport","unitId":17,"cells":[{"column":36,"numberValue":52.00000000000000}],"excludeFromChart":true}]},{"id":100118,"name":"Guatemala","rows":[{"id":14435,"name":"1.A.3  Transport","unitId":17,"cells":[{"column":32,"numberValue":2134.98900000000000},{"column":36,"numberValue":3130.73300000000000},{"column":42,"numberValue":4513.02300000000000},{"column":47,"numberValue":6012.87200000000000}],"excludeFromChart":true}]},{"id":100119,"name":"Guinea","rows":[{"id":14435,"name":"1.A.3  Transport","unitId":17,"cells":[{"column":36,"numberValue":625.18400000000000},{"column":42,"numberValue":522.00000000000000}],"excludeFromChart":true}]},{"id":100120,"name":"Guinea-Bissau","rows":[{"id":14435,"name":"1.A.3  Transport","unitId":17,"cells":[{"column":36,"numberValue":0.41500000000000},{"column":52,"numberValue":96.43000000000000}],"excludeFromChart":true}]},{"id":100121,"name":"Guyana","rows":[{"id":14435,"name":"1.A.3  Transport","unitId":17,"cells":[{"column":32,"numberValue":210.00000000000000},{"column":33,"numberValue":210.00000000000000},{"column":34,"numberValue":210.00000000000000},{"column":35,"numberValue":210.00000000000000},{"column":36,"numberValue":210.00000000000000},{"column":37,"numberValue":215.00000000000000},{"column":38,"numberValue":267.00000000000000},{"column":39,"numberValue":275.00000000000000},{"column":40,"numberValue":310.00000000000000},{"column":41,"numberValue":323.00000000000000},{"column":42,"numberValue":335.00000000000000},{"column":43,"numberValue":326.00000000000000},{"column":44,"numberValue":314.00000000000000},{"column":45,"numberValue":314.00000000000000},{"column":46,"numberValue":314.00000000000000}],"excludeFromChart":true}]},{"id":100122,"name":"Haiti","rows":[{"id":14435,"name":"1.A.3  Transport","unitId":17,"cells":[{"column":36,"numberValue":115.45000000000000},{"column":37,"numberValue":540.14000000000000},{"column":38,"numberValue":532.28000000000000},{"column":39,"numberValue":640.78000000000000},{"column":40,"numberValue":633.19000000000000},{"column":41,"numberValue":821.01000000000000},{"column":42,"numberValue":749.87000000000000}],"excludeFromChart":true}]},{"id":100123,"name":"Honduras","rows":[{"id":14435,"name":"1.A.3  Transport","unitId":17,"cells":[{"column":37,"numberValue":12.75650000000000},{"column":42,"numberValue":2273.00000000000000},{"column":47,"numberValue":2232.52000000000000},{"column":57,"numberValue":4107.67000000000000}],"excludeFromChart":true}]},{"id":100124,"name":"India","rows":[{"id":14435,"name":"1.A.3  Transport","unitId":17,"cells":[{"column":36,"numberValue":80286.00000000000000},{"column":42,"numberValue":98104.53000000000000},{"column":52,"numberValue":188009.00000000000000},{"column":58,"numberValue":274557.00000000000000}],"excludeFromChart":true}]},{"id":100125,"name":"Indonesia","rows":[{"id":14435,"name":"1.A.3  Transport","unitId":17,"cells":[{"column":32,"numberValue":34808.64000000000000},{"column":33,"numberValue":37816.79000000000000},{"column":34,"numberValue":40133.71000000000000},{"column":35,"numberValue":42271.64000000000000},{"column":36,"numberValue":47340.85000000000000},{"column":42,"numberValue":56820.75000000000000}],"excludeFromChart":true}]},{"id":100126,"name":"Iran (Islamic Republic of)","rows":[{"id":14435,"name":"1.A.3  Transport","unitId":17,"cells":[{"column":36,"numberValue":60606.23000000000000},{"column":42,"numberValue":76005.15000000000000}],"excludeFromChart":true}]},{"id":100127,"name":"Iraq","rows":[{"id":14435,"name":"1.A.3  Transport","unitId":17,"cells":[{"column":39,"numberValue":18518.00000000000000}],"excludeFromChart":true}]},{"id":100128,"name":"Israel","rows":[{"id":14435,"name":"1.A.3  Transport","unitId":17,"cells":[{"column":38,"numberValue":11112.36700000000000},{"column":42,"numberValue":14108.72248996000000},{"column":45,"numberValue":14718.89668851170000},{"column":46,"numberValue":14411.98347778120000},{"column":47,"numberValue":14207.92269636430000},{"column":48,"numberValue":14643.21713817180000},{"column":49,"numberValue":15296.49505408580000},{"column":50,"numberValue":15446.66355498210000},{"column":51,"numberValue":15652.24079533240000},{"column":52,"numberValue":16292.88363741660000},{"column":53,"numberValue":16179.82902758790000},{"column":54,"numberValue":16482.13450323290000},{"column":55,"numberValue":16735.37330206460000},{"column":56,"numberValue":16769.96187038440000},{"column":57,"numberValue":17615.88877973290000},{"column":58,"numberValue":18109.94254913640000},{"column":59,"numberValue":18580.46650583320000},{"column":60,"numberValue":18698.50217557260000}],"excludeFromChart":true}]},{"id":100129,"name":"Jamaica","rows":[{"id":14435,"name":"1.A.3  Transport","unitId":17,"cells":[{"column":36,"numberValue":1268.69000000000000},{"column":48,"numberValue":2188.11000000000000},{"column":49,"numberValue":2108.24000000000000},{"column":50,"numberValue":1998.68000000000000},{"column":51,"numberValue":2071.43000000000000},{"column":52,"numberValue":1977.39000000000000},{"column":54,"numberValue":1806.18000000000000}],"excludeFromChart":true}]},{"id":100130,"name":"Jordan","rows":[{"id":14435,"name":"1.A.3  Transport","unitId":17,"cells":[{"column":36,"numberValue":2849.85451000000000},{"column":42,"numberValue":3623.50600000000000},{"column":48,"numberValue":4727.00000000000000},{"column":58,"numberValue":8786.50100000000000}],"excludeFromChart":true}]},{"id":100132,"name":"Kenya","rows":[{"id":14435,"name":"1.A.3  Transport","unitId":17,"cells":[{"column":37,"numberValue":3495.30000000000000},{"column":42,"numberValue":3781.30000000000000},{"column":47,"numberValue":4342.30000000000000},{"column":52,"numberValue":7373.50000000000000}],"excludeFromChart":true}]},{"id":100133,"name":"Kiribati","rows":[{"id":14435,"name":"1.A.3  Transport","unitId":17,"cells":[{"column":46,"numberValue":13.87560000000000},{"column":47,"numberValue":14.35330000000000},{"column":48,"numberValue":31.27630000000000},{"column":49,"numberValue":32.59080000000000},{"column":50,"numberValue":31.21620000000000}],"excludeFromChart":true}]},{"id":100134,"name":"Kuwait","rows":[{"id":14435,"name":"1.A.3  Transport","unitId":17,"cells":[{"column":36,"numberValue":5393.38000000000000},{"column":58,"numberValue":15000.77900000000000}],"excludeFromChart":true}]},{"id":100135,"name":"Kyrgyzstan","rows":[{"id":14435,"name":"1.A.3  Transport","unitId":17,"cells":[{"column":32,"numberValue":3176.69450000000000},{"column":33,"numberValue":2725.13020000000000},{"column":34,"numberValue":2273.58790000000000},{"column":35,"numberValue":1822.02360000000000},{"column":36,"numberValue":1370.46030000000000},{"column":37,"numberValue":918.88900000000000},{"column":38,"numberValue":1086.10550000000000},{"column":39,"numberValue":1253.30510000000000},{"column":40,"numberValue":1153.23990000000000},{"column":41,"numberValue":1053.15580000000000},{"column":42,"numberValue":956.34550000000000},{"column":43,"numberValue":859.50620000000000},{"column":44,"numberValue":933.35550000000000},{"column":45,"numberValue":1007.17380000000000},{"column":46,"numberValue":1080.99610000000000},{"column":47,"numberValue":1154.84030000000000},{"column":48,"numberValue":1208.28890000000000},{"column":49,"numberValue":1813.52570000000000},{"column":50,"numberValue":2051.46010000000000},{"column":51,"numberValue":2444.71190000000000},{"column":52,"numberValue":2147.68550000000000}],"excludeFromChart":true}]},{"id":100136,"name":"Lao People's Democratic Republic","rows":[{"id":14435,"name":"1.A.3  Transport","unitId":17,"cells":[{"column":42,"numberValue":446.61000000000000}],"excludeFromChart":true}]},{"id":100137,"name":"Lebanon","rows":[{"id":14435,"name":"1.A.3  Transport","unitId":17,"cells":[{"column":36,"numberValue":3991.40790000000000},{"column":42,"numberValue":3962.64000000000000},{"column":53,"numberValue":5813.43000000000000},{"column":54,"numberValue":5980.17000000000000},{"column":55,"numberValue":6158.36000000000000}],"excludeFromChart":true}]},{"id":100138,"name":"Lesotho","rows":[{"id":14435,"name":"1.A.3  Transport","unitId":17,"cells":[{"column":36,"numberValue":221.74000000000000}],"excludeFromChart":true}]},{"id":100139,"name":"Liberia","rows":[{"id":14435,"name":"1.A.3  Transport","unitId":17,"cells":[{"column":42,"numberValue":2173.00000000000000},{"column":56,"numberValue":17477.00000000000000}],"excludeFromChart":true}]},{"id":100140,"name":"Libya","rows":[{"id":14435,"name":"1.A.3  Transport","unitId":null,"cells":[],"excludeFromChart":true}]},{"id":100141,"name":"Madagascar","rows":[{"id":14435,"name":"1.A.3  Transport","unitId":17,"cells":[{"column":36,"numberValue":618.52000000000000},{"column":42,"numberValue":938.70000000000000},{"column":47,"numberValue":943.30000000000000},{"column":48,"numberValue":879.90000000000000},{"column":49,"numberValue":941.80000000000000},{"column":50,"numberValue":972.30000000000000},{"column":51,"numberValue":920.20000000000000},{"column":52,"numberValue":990.10000000000000}],"excludeFromChart":true}]},{"id":100142,"name":"Malawi","rows":[{"id":14435,"name":"1.A.3  Transport","unitId":null,"cells":[],"excludeFromChart":true}]},{"id":100143,"name":"Malaysia","rows":[{"id":14435,"name":"1.A.3  Transport","unitId":17,"cells":[{"column":32,"numberValue":16004.85000000000000},{"column":33,"numberValue":17251.36000000000000},{"column":34,"numberValue":18506.71000000000000},{"column":35,"numberValue":19455.70000000000000},{"column":36,"numberValue":21516.51000000000000},{"column":37,"numberValue":23175.25000000000000},{"column":38,"numberValue":26491.75000000000000},{"column":39,"numberValue":30261.43000000000000},{"column":40,"numberValue":28932.23000000000000},{"column":41,"numberValue":33701.34000000000000},{"column":42,"numberValue":35851.33000000000000},{"column":43,"numberValue":39030.15000000000000},{"column":44,"numberValue":39925.23000000000000},{"column":45,"numberValue":42388.35000000000000},{"column":46,"numberValue":45695.94000000000000},{"column":47,"numberValue":45608.51000000000000},{"column":48,"numberValue":43987.15000000000000},{"column":49,"numberValue":46521.99000000000000},{"column":50,"numberValue":48503.50000000000000},{"column":51,"numberValue":47657.26000000000000},{"column":52,"numberValue":49637.58000000000000},{"column":53,"numberValue":44310.00000000000000}],"excludeFromChart":true}]},{"id":100144,"name":"Maldives","rows":[{"id":14435,"name":"1.A.3  Transport","unitId":17,"cells":[{"column":53,"numberValue":301.44800000000000},{"column":54,"numberValue":313.69200000000000},{"column":55,"numberValue":344.46600000000000},{"column":56,"numberValue":367.37000000000000},{"column":57,"numberValue":380.99100000000000}],"excludeFromChart":true}]},{"id":100145,"name":"Mali","rows":[{"id":14435,"name":"1.A.3  Transport","unitId":17,"cells":[{"column":42,"numberValue":677.87000000000000},{"column":52,"numberValue":1754.64300000000000}],"excludeFromChart":true}]},{"id":100146,"name":"Marshall Islands","rows":[{"id":14435,"name":"1.A.3  Transport","unitId":17,"cells":[{"column":42,"numberValue":15.92468000000000},{"column":47,"numberValue":17.47775000000000},{"column":52,"numberValue":22.54185000000000}],"excludeFromChart":true}]},{"id":100147,"name":"Mauritania","rows":[{"id":14435,"name":"1.A.3  Transport","unitId":17,"cells":[{"column":37,"numberValue":296.37509690000000},{"column":42,"numberValue":405.16860000000000}],"excludeFromChart":true}]},{"id":100148,"name":"Mauritius","rows":[{"id":14435,"name":"1.A.3  Transport","unitId":17,"cells":[{"column":37,"numberValue":647.09400000000000},{"column":42,"numberValue":732.65710000000000},{"column":43,"numberValue":748.71160000000000},{"column":44,"numberValue":769.83280000000000},{"column":45,"numberValue":796.56060000000000},{"column":46,"numberValue":814.03580000000000},{"column":47,"numberValue":844.64670000000000},{"column":48,"numberValue":1299.25000000000000},{"column":55,"numberValue":1363.64000000000000}],"excludeFromChart":true}]},{"id":100149,"name":"Mexico","rows":[{"id":14435,"name":"1.A.3  Transport","unitId":17,"cells":[{"column":32,"numberValue":89675.64000000000000},{"column":33,"numberValue":95844.92000000000000},{"column":34,"numberValue":96716.69000000000000},{"column":35,"numberValue":99150.40000000000000},{"column":36,"numberValue":103521.87000000000000},{"column":37,"numberValue":98368.47000000000000},{"column":38,"numberValue":99743.09000000000000},{"column":39,"numberValue":103724.99000000000000},{"column":40,"numberValue":107018.43000000000000},{"column":41,"numberValue":108415.08000000000000},{"column":42,"numberValue":112659.06000000000000},{"column":43,"numberValue":113025.29000000000000},{"column":44,"numberValue":113527.62000000000000},{"column":45,"numberValue":120210.93000000000000},{"column":46,"numberValue":128351.43000000000000},{"column":47,"numberValue":133047.15000000000000},{"column":48,"numberValue":141355.77000000000000},{"column":49,"numberValue":152326.74000000000000},{"column":50,"numberValue":161134.97000000000000},{"column":51,"numberValue":154349.17000000000000},{"column":52,"numberValue":157315.46000000000000},{"column":53,"numberValue":160472.80000000000000},{"column":54,"numberValue":160194.14000000000000},{"column":55,"numberValue":171629.31000000000000}],"excludeFromChart":true}]},{"id":100150,"name":"Micronesia (Federated States of)","rows":[{"id":14435,"name":"1.A.3  Transport","unitId":17,"cells":[{"column":36,"numberValue":0.64069200000000}],"excludeFromChart":true}]},{"id":100152,"name":"Mongolia","rows":[{"id":14435,"name":"1.A.3  Transport","unitId":17,"cells":[{"column":48,"numberValue":1886.93000000000000}],"excludeFromChart":true}]},{"id":100153,"name":"Montenegro","rows":[{"id":14435,"name":"1.A.3  Transport","unitId":17,"cells":[{"column":32,"numberValue":334.50000000000000},{"column":33,"numberValue":294.50000000000000},{"column":34,"numberValue":231.50000000000000},{"column":35,"numberValue":180.60000000000000},{"column":36,"numberValue":149.20000000000000},{"column":37,"numberValue":162.30000000000000},{"column":38,"numberValue":263.00000000000000},{"column":39,"numberValue":293.30000000000000},{"column":40,"numberValue":412.30000000000000},{"column":41,"numberValue":502.90000000000000},{"column":42,"numberValue":503.20000000000000},{"column":43,"numberValue":437.70000000000000},{"column":44,"numberValue":357.00000000000000},{"column":45,"numberValue":373.10000000000000},{"column":46,"numberValue":423.00000000000000},{"column":47,"numberValue":451.60000000000000},{"column":48,"numberValue":533.00000000000000},{"column":49,"numberValue":609.00000000000000},{"column":50,"numberValue":634.90000000000000},{"column":51,"numberValue":758.60000000000000},{"column":52,"numberValue":737.70000000000000},{"column":53,"numberValue":541.21000000000000}],"excludeFromChart":true}]},{"id":100154,"name":"Morocco","rows":[{"id":14435,"name":"1.A.3  Transport","unitId":17,"cells":[{"column":36,"numberValue":5836.00000000000000},{"column":42,"numberValue":5962.99000000000000},{"column":46,"numberValue":6557.50000000000000},{"column":47,"numberValue":10437.20000000000000},{"column":48,"numberValue":10762.50000000000000},{"column":50,"numberValue":12306.30000000000000},{"column":52,"numberValue":13857.50000000000000},{"column":54,"numberValue":14814.18000000000000}],"excludeFromChart":true}]},{"id":100155,"name":"Mozambique","rows":[{"id":14435,"name":"1.A.3  Transport","unitId":17,"cells":[{"column":36,"numberValue":854.78000000000000}],"excludeFromChart":true}]},{"id":100156,"name":"Myanmar","rows":[{"id":14435,"name":"1.A.3  Transport","unitId":17,"cells":[{"column":42,"numberValue":2170.64000000000000},{"column":43,"numberValue":2016.84000000000000},{"column":44,"numberValue":2533.91000000000000},{"column":45,"numberValue":2656.89000000000000},{"column":46,"numberValue":2553.67000000000000},{"column":47,"numberValue":2480.99000000000000}],"excludeFromChart":true}]},{"id":100157,"name":"Namibia","rows":[{"id":14435,"name":"1.A.3  Transport","unitId":17,"cells":[{"column":36,"numberValue":905.86000000000000},{"column":42,"numberValue":1029.20000000000000}],"excludeFromChart":true}]},{"id":100158,"name":"Nauru","rows":[{"id":14435,"name":"1.A.3  Transport","unitId":17,"cells":[{"column":42,"numberValue":3.33145700000000},{"column":45,"numberValue":18.21053900000000},{"column":49,"numberValue":4.48288300000000},{"column":52,"numberValue":7.30671100000000}],"excludeFromChart":true}]},{"id":100159,"name":"Nepal","rows":[{"id":14435,"name":"1.A.3  Transport","unitId":17,"cells":[{"column":36,"numberValue":456.00000000000000},{"column":42,"numberValue":822.62000000000000}],"excludeFromChart":true}]},{"id":100160,"name":"Nicaragua","rows":[{"id":14435,"name":"1.A.3  Transport","unitId":17,"cells":[{"column":36,"numberValue":841.57000000000000},{"column":42,"numberValue":1234.51400000000000}],"excludeFromChart":true}]},{"id":100161,"name":"Niger","rows":[{"id":14435,"name":"1.A.3  Transport","unitId":17,"cells":[{"column":32,"numberValue":232.40000000000000},{"column":42,"numberValue":757.00000000000000},{"column":50,"numberValue":532.00000000000000}],"excludeFromChart":true}]},{"id":100162,"name":"Nigeria","rows":[{"id":14435,"name":"1.A.3  Transport","unitId":17,"cells":[{"column":36,"numberValue":36855.47798977290000}],"excludeFromChart":true}]},{"id":100163,"name":"Niue","rows":[{"id":14435,"name":"1.A.3  Transport","unitId":17,"cells":[{"column":36,"numberValue":1.42200382000000},{"column":42,"numberValue":1.93240000000000},{"column":47,"numberValue":2.95760000000000},{"column":48,"numberValue":4.32880000000000},{"column":49,"numberValue":5.74000000000000},{"column":50,"numberValue":2.45460000000000},{"column":51,"numberValue":2.91470000000000}],"excludeFromChart":true}]},{"id":100199,"name":"North Macedonia","rows":[{"id":14435,"name":"1.A.3  Transport","unitId":17,"cells":[{"column":32,"numberValue":1055.28163717980000},{"column":33,"numberValue":1032.77470048980000},{"column":34,"numberValue":860.09589544980000},{"column":35,"numberValue":1209.43009231840000},{"column":36,"numberValue":1097.03993500560000},{"column":37,"numberValue":1095.38492113360000},{"column":38,"numberValue":1145.56873100740000},{"column":39,"numberValue":1122.58402160580000},{"column":40,"numberValue":1060.32546208963000},{"column":41,"numberValue":1190.17406906254000},{"column":42,"numberValue":1067.52105076721000},{"column":43,"numberValue":1010.66344526474000},{"column":44,"numberValue":1083.28269764926000},{"column":45,"numberValue":1168.21000000000000},{"column":46,"numberValue":1012.60000000000000},{"column":47,"numberValue":1019.10000000000000},{"column":48,"numberValue":1018.78000000000000},{"column":49,"numberValue":1165.07000000000000},{"column":50,"numberValue":1200.05000000000000},{"column":51,"numberValue":1294.04000000000000}],"excludeFromChart":true}]},{"id":100164,"name":"Oman","rows":[{"id":14435,"name":"1.A.3  Transport","unitId":17,"cells":[{"column":36,"numberValue":1656.62000000000000}],"excludeFromChart":true}]},{"id":100165,"name":"Pakistan","rows":[{"id":14435,"name":"1.A.3  Transport","unitId":17,"cells":[{"column":57,"numberValue":41197.00000000000000}],"excludeFromChart":true}]},{"id":100166,"name":"Palau","rows":[{"id":14435,"name":"1.A.3  Transport","unitId":17,"cells":[{"column":42,"stringValue":"IE,NE"}],"excludeFromChart":true}]},{"id":100167,"name":"Panama","rows":[{"id":14435,"name":"1.A.3  Transport","unitId":17,"cells":[{"column":36,"numberValue":1488.86000000000000},{"column":42,"numberValue":2726.10000000000000}],"excludeFromChart":true}]},{"id":100168,"name":"Papua New Guinea","rows":[{"id":14435,"name":"1.A.3  Transport","unitId":null,"cells":[],"excludeFromChart":true}]},{"id":100169,"name":"Paraguay","rows":[{"id":14435,"name":"1.A.3  Transport","unitId":17,"cells":[{"column":32,"numberValue":1727.63170000000000},{"column":36,"numberValue":2570.11000000000000},{"column":42,"numberValue":2789.29000000000000},{"column":47,"numberValue":3030.35000000000000},{"column":53,"numberValue":3776.69000000000000},{"column":54,"numberValue":4534.88000000000000},{"column":57,"numberValue":5450.79000000000000},{"column":59,"numberValue":7224.40000000000000}],"excludeFromChart":true}]},{"id":100170,"name":"Peru","rows":[{"id":14435,"name":"1.A.3  Transport","unitId":17,"cells":[{"column":36,"numberValue":7969.79000000000000},{"column":42,"numberValue":9938.00000000000000},{"column":52,"numberValue":15205.70000000000000},{"column":54,"numberValue":17847.00000000000000}],"excludeFromChart":true}]},{"id":100171,"name":"Philippines","rows":[{"id":14435,"name":"1.A.3  Transport","unitId":17,"cells":[{"column":36,"numberValue":15889.55000000000000},{"column":42,"numberValue":25935.78000000000000}],"excludeFromChart":true}]},{"id":100172,"name":"Qatar","rows":[{"id":14435,"name":"1.A.3  Transport","unitId":17,"cells":[{"column":49,"numberValue":5342.11100000000000}],"excludeFromChart":true}]},{"id":100173,"name":"Republic of Korea","rows":[{"id":14435,"name":"1.A.3  Transport","unitId":17,"cells":[{"column":32,"numberValue":35493.00000000000000},{"column":33,"numberValue":38596.15000000000000},{"column":34,"numberValue":43959.14000000000000},{"column":35,"numberValue":55551.98000000000000},{"column":36,"numberValue":57567.07000000000000},{"column":37,"numberValue":64727.30000000000000},{"column":38,"numberValue":68801.90000000000000},{"column":39,"numberValue":74192.74000000000000},{"column":40,"numberValue":57544.08000000000000},{"column":41,"numberValue":62563.48000000000000},{"column":42,"numberValue":69909.32000000000000},{"column":43,"numberValue":73063.03000000000000},{"column":44,"numberValue":78043.58000000000000},{"column":45,"numberValue":80845.18000000000000},{"column":46,"numberValue":80997.17000000000000},{"column":47,"numberValue":81813.53000000000000},{"column":48,"numberValue":82629.80000000000000},{"column":49,"numberValue":85027.41000000000000},{"column":50,"numberValue":82852.57000000000000},{"column":51,"numberValue":83723.95000000000000},{"column":52,"numberValue":85443.69000000000000},{"column":53,"numberValue":85115.38000000000000},{"column":54,"numberValue":86479.32000000000000},{"column":55,"numberValue":88403.69000000000000},{"column":56,"numberValue":88715.46000000000000},{"column":57,"numberValue":94193.43000000000000},{"column":58,"numberValue":98714.02000000000000}],"excludeFromChart":true}]},{"id":100174,"name":"Republic of Moldova","rows":[{"id":14435,"name":"1.A.3  Transport","unitId":17,"cells":[{"column":32,"numberValue":4056.61150000000000},{"column":33,"numberValue":3663.98080000000000},{"column":34,"numberValue":2052.01650000000000},{"column":35,"numberValue":1513.98340000000000},{"column":36,"numberValue":1317.56570000000000},{"column":37,"numberValue":1338.35780000000000},{"column":38,"numberValue":1305.85340000000000},{"column":39,"numberValue":1331.66640000000000},{"column":40,"numberValue":1161.53920000000000},{"column":41,"numberValue":792.18100000000000},{"column":42,"numberValue":863.47360000000000},{"column":43,"numberValue":920.48680000000000},{"column":44,"numberValue":1166.75470000000000},{"column":45,"numberValue":1455.76870000000000},{"column":46,"numberValue":1624.96410000000000},{"column":47,"numberValue":1656.74590000000000},{"column":48,"numberValue":1582.09770000000000},{"column":49,"numberValue":1651.37170000000000},{"column":50,"numberValue":1742.52840000000000},{"column":51,"numberValue":1659.11940000000000},{"column":52,"numberValue":1905.69940000000000},{"column":53,"numberValue":2020.23920000000000},{"column":54,"numberValue":1763.40150000000000},{"column":55,"numberValue":1877.17640000000000}],"excludeFromChart":true}]},{"id":100175,"name":"Rwanda","rows":[{"id":14435,"name":"1.A.3  Transport","unitId":17,"cells":[{"column":47,"numberValue":274.00000000000000}],"excludeFromChart":true}]},{"id":100176,"name":"Saint Kitts and Nevis","rows":[{"id":14435,"name":"1.A.3  Transport","unitId":17,"cells":[{"column":36,"numberValue":26.27000000000000}],"excludeFromChart":true}]},{"id":100177,"name":"Saint Lucia","rows":[{"id":14435,"name":"1.A.3  Transport","unitId":17,"cells":[{"column":36,"numberValue":105.51692000000000},{"column":42,"numberValue":135.70090000000000},{"column":47,"numberValue":159.97290000000000},{"column":52,"numberValue":202.19140000000000}],"excludeFromChart":true}]},{"id":100178,"name":"Saint Vincent and the Grenadines","rows":[{"id":14435,"name":"1.A.3  Transport","unitId":17,"cells":[{"column":32,"numberValue":28.38400000000000},{"column":36,"numberValue":33.94400000000000},{"column":39,"numberValue":37.89400000000000},{"column":42,"numberValue":66.79000000000000},{"column":46,"numberValue":3.15000000000000}],"excludeFromChart":true}]},{"id":100179,"name":"Samoa","rows":[{"id":14435,"name":"1.A.3  Transport","unitId":17,"cells":[{"column":36,"numberValue":71.23269530000000}],"excludeFromChart":true}]},{"id":100180,"name":"San Marino","rows":[{"id":14435,"name":"1.A.3  Transport","unitId":17,"cells":[{"column":49,"numberValue":139.67000000000000},{"column":52,"numberValue":159.29000000000000}],"excludeFromChart":true}]},{"id":100181,"name":"Sao Tome and Principe","rows":[{"id":14435,"name":"1.A.3  Transport","unitId":17,"cells":[{"column":40,"numberValue":22.20000000000000},{"column":47,"numberValue":28.30000000000000},{"column":54,"numberValue":37.49900000000000}],"excludeFromChart":true}]},{"id":100182,"name":"Saudi Arabia","rows":[{"id":14435,"name":"1.A.3  Transport","unitId":17,"cells":[{"column":32,"numberValue":40176.24970000000000},{"column":42,"numberValue":58092.86000000000000},{"column":52,"numberValue":105987.97680000000000},{"column":54,"numberValue":121290.26000000000000}],"excludeFromChart":true}]},{"id":100183,"name":"Senegal","rows":[{"id":14435,"name":"1.A.3  Transport","unitId":17,"cells":[{"column":42,"numberValue":1920.81000000000000},{"column":47,"numberValue":1468.19000000000000}],"excludeFromChart":true}]},{"id":100184,"name":"Serbia","rows":[{"id":14435,"name":"1.A.3  Transport","unitId":17,"cells":[{"column":32,"numberValue":5715.34000000000000},{"column":40,"numberValue":3876.70000000000000}],"excludeFromChart":true}]},{"id":100185,"name":"Seychelles","rows":[{"id":14435,"name":"1.A.3  Transport","unitId":17,"cells":[{"column":37,"numberValue":55.35400000000000},{"column":42,"numberValue":66.44678000000000}],"excludeFromChart":true}]},{"id":100186,"name":"Sierra Leone","rows":[{"id":14435,"name":"1.A.3  Transport","unitId":null,"cells":[],"excludeFromChart":true}]},{"id":100187,"name":"Singapore","rows":[{"id":14435,"name":"1.A.3  Transport","unitId":17,"cells":[{"column":36,"numberValue":4099.99000000000000},{"column":42,"numberValue":5810.82500000000000},{"column":52,"numberValue":6960.76999994500000},{"column":54,"numberValue":7189.62000000000000}],"excludeFromChart":true}]},{"id":100188,"name":"Solomon Islands","rows":[{"id":14435,"name":"1.A.3  Transport","unitId":17,"cells":[{"column":36,"numberValue":192.79000000000000},{"column":42,"numberValue":88.67767000000000},{"column":47,"numberValue":112.59000000000000},{"column":52,"numberValue":176.91000000000000}],"excludeFromChart":true}]},{"id":100189,"name":"Somalia","rows":[{"id":14435,"name":"1.A.3  Transport","unitId":null,"cells":[],"excludeFromChart":true}]},{"id":100190,"name":"South Africa","rows":[{"id":14435,"name":"1.A.3  Transport","unitId":17,"cells":[{"column":32,"numberValue":31544.01000000000000},{"column":36,"numberValue":43521.67000000000000}],"excludeFromChart":true}]},{"id":100191,"name":"South Sudan","rows":[{"id":14435,"name":"1.A.3  Transport","unitId":17,"cells":[{"column":54,"numberValue":676.26610000000000},{"column":55,"numberValue":548.78360000000000},{"column":56,"numberValue":394.78780000000000},{"column":57,"numberValue":447.95020000000000}],"excludeFromChart":true}]},{"id":100192,"name":"Sri Lanka","rows":[{"id":14435,"name":"1.A.3  Transport","unitId":17,"cells":[{"column":36,"numberValue":2988.00450000000000},{"column":42,"numberValue":5083.77000000000000}],"excludeFromChart":true}]},{"id":100229,"name":"State of Palestine","rows":[{"id":14435,"name":"1.A.3  Transport","unitId":17,"cells":[{"column":53,"numberValue":948.27830000000000}],"excludeFromChart":true}]},{"id":100193,"name":"Sudan","rows":[{"id":14435,"name":"1.A.3  Transport","unitId":17,"cells":[{"column":37,"numberValue":1923.00000000000000},{"column":42,"numberValue":2851.00000000000000}],"excludeFromChart":true}]},{"id":100194,"name":"Suriname","rows":[{"id":14435,"name":"1.A.3  Transport","unitId":17,"cells":[{"column":45,"numberValue":351.00000000000000}],"excludeFromChart":true}]},{"id":100196,"name":"Syrian Arab Republic","rows":[{"id":14435,"name":"1.A.3  Transport","unitId":null,"cells":[],"excludeFromChart":true}]},{"id":100197,"name":"Tajikistan","rows":[{"id":14435,"name":"1.A.3  Transport","unitId":17,"cells":[{"column":32,"numberValue":4797.00000000000000},{"column":33,"numberValue":4776.00000000000000},{"column":34,"numberValue":2965.40000000000000},{"column":35,"numberValue":1401.00000000000000},{"column":36,"numberValue":1144.00000000000000},{"column":37,"numberValue":465.00000000000000},{"column":38,"numberValue":418.00000000000000},{"column":39,"numberValue":501.00000000000000},{"column":40,"numberValue":543.00000000000000},{"column":41,"numberValue":454.00000000000000},{"column":42,"numberValue":224.00000000000000},{"column":43,"numberValue":400.00000000000000},{"column":44,"numberValue":514.00000000000000},{"column":45,"numberValue":304.00000000000000},{"column":46,"numberValue":511.00000000000000},{"column":47,"numberValue":497.00000000000000},{"column":48,"numberValue":598.00000000000000},{"column":49,"numberValue":385.00000000000000},{"column":50,"numberValue":314.00000000000000},{"column":51,"numberValue":372.00000000000000},{"column":52,"numberValue":406.00000000000000}],"excludeFromChart":true}]},{"id":100198,"name":"Thailand","rows":[{"id":14435,"name":"1.A.3  Transport","unitId":17,"cells":[{"column":36,"numberValue":39922.29000000000000},{"column":55,"numberValue":61175.27000000000000}],"excludeFromChart":true}]},{"id":100200,"name":"Timor-Leste","rows":[{"id":14435,"name":"1.A.3  Transport","unitId":17,"cells":[{"column":52,"numberValue":110.30000000000000}],"excludeFromChart":true}]},{"id":100201,"name":"Togo","rows":[{"id":14435,"name":"1.A.3  Transport","unitId":17,"cells":[{"column":37,"numberValue":570.41000000000000},{"column":42,"numberValue":642.03000000000000},{"column":47,"numberValue":783.67000000000000}],"excludeFromChart":true}]},{"id":100202,"name":"Tonga","rows":[{"id":14435,"name":"1.A.3  Transport","unitId":17,"cells":[{"column":36,"numberValue":46.49000000000000},{"column":42,"numberValue":56.41740000000000},{"column":48,"numberValue":68.04000000000000}],"excludeFromChart":true}]},{"id":100203,"name":"Trinidad and Tobago","rows":[{"id":14435,"name":"1.A.3  Transport","unitId":17,"cells":[{"column":32,"numberValue":1489.02800000000000}],"excludeFromChart":true}]},{"id":100204,"name":"Tunisia","rows":[{"id":14435,"name":"1.A.3  Transport","unitId":17,"cells":[{"column":36,"numberValue":3408.45400000000000},{"column":42,"numberValue":5158.97000000000000}],"excludeFromChart":true}]},{"id":100205,"name":"Turkmenistan","rows":[{"id":14435,"name":"1.A.3  Transport","unitId":17,"cells":[{"column":36,"numberValue":878.73200000000000},{"column":42,"numberValue":4922.15520000000000},{"column":46,"numberValue":2371.13400000000000},{"column":52,"numberValue":7040.71910000000000}],"excludeFromChart":true}]},{"id":100206,"name":"Tuvalu","rows":[{"id":14435,"name":"1.A.3  Transport","unitId":17,"cells":[{"column":56,"numberValue":3.95763000000000}],"excludeFromChart":true}]},{"id":100207,"name":"Uganda","rows":[{"id":14435,"name":"1.A.3  Transport","unitId":17,"cells":[{"column":36,"numberValue":677.19600000000000},{"column":42,"numberValue":808.00000000000000}],"excludeFromChart":true}]},{"id":100208,"name":"United Arab Emirates","rows":[{"id":14435,"name":"1.A.3  Transport","unitId":17,"cells":[{"column":36,"numberValue":17900.00000000000000},{"column":42,"numberValue":17665.00000000000000},{"column":47,"numberValue":29223.00000000000000},{"column":56,"numberValue":33232.17000000000000}],"excludeFromChart":true}]},{"id":100209,"name":"United Republic of Tanzania","rows":[{"id":14435,"name":"1.A.3  Transport","unitId":17,"cells":[{"column":32,"numberValue":1716.67640000000000},{"column":36,"numberValue":1673.17930000000000}],"excludeFromChart":true}]},{"id":100210,"name":"Uruguay","rows":[{"id":14435,"name":"1.A.3  Transport","unitId":17,"cells":[{"column":40,"numberValue":2727.69000000000000},{"column":44,"numberValue":2210.42000000000000},{"column":48,"numberValue":2425.77000000000000},{"column":50,"numberValue":2707.60000000000000},{"column":56,"numberValue":3521.80000000000000},{"column":58,"numberValue":3660.70000000000000},{"column":59,"numberValue":3803.30000000000000}],"excludeFromChart":true}]},{"id":100211,"name":"Uzbekistan","rows":[{"id":14435,"name":"1.A.3  Transport","unitId":17,"cells":[{"column":32,"numberValue":16573.70000000000000},{"column":33,"numberValue":15242.30000000000000},{"column":34,"numberValue":11331.70000000000000},{"column":35,"numberValue":9854.00000000000000},{"column":36,"numberValue":8765.10000000000000},{"column":37,"numberValue":8172.70000000000000},{"column":38,"numberValue":8394.40000000000000},{"column":39,"numberValue":8612.70000000000000},{"column":40,"numberValue":9140.90000000000000},{"column":41,"numberValue":10431.70000000000000},{"column":42,"numberValue":11179.20000000000000},{"column":43,"numberValue":12989.30000000000000},{"column":44,"numberValue":12614.30000000000000},{"column":45,"numberValue":11184.00000000000000},{"column":46,"numberValue":10181.30000000000000},{"column":47,"numberValue":9639.30000000000000},{"column":48,"numberValue":12634.30000000000000},{"column":49,"numberValue":12991.20000000000000},{"column":50,"numberValue":13895.80000000000000},{"column":51,"numberValue":13310.20000000000000},{"column":52,"numberValue":12804.84000000000000},{"column":53,"numberValue":12145.90000000000000},{"column":54,"numberValue":12436.86000000000000}],"excludeFromChart":true}]},{"id":100212,"name":"Vanuatu","rows":[{"id":14435,"name":"1.A.3  Transport","unitId":17,"cells":[{"column":36,"numberValue":45.29244196000000},{"column":42,"numberValue":34.50000000000000}],"excludeFromChart":true}]},{"id":100213,"name":"Venezuela (Bolivarian Republic of)","rows":[{"id":14435,"name":"1.A.3  Transport","unitId":17,"cells":[{"column":41,"numberValue":33991.00000000000000}],"excludeFromChart":true}]},{"id":100214,"name":"Viet Nam","rows":[{"id":14435,"name":"1.A.3  Transport","unitId":17,"cells":[{"column":36,"numberValue":3657.52500000000000},{"column":42,"numberValue":11946.61000000000000},{"column":52,"numberValue":31817.89000000000000},{"column":55,"numberValue":29680.72000000000000}],"excludeFromChart":true}]},{"id":100215,"name":"Yemen","rows":[{"id":14435,"name":"1.A.3  Transport","unitId":17,"cells":[{"column":37,"numberValue":3850.57000000000000},{"column":42,"numberValue":4956.00000000000000},{"column":52,"numberValue":7180.74000000000000},{"column":54,"numberValue":5739.01000000000000}],"excludeFromChart":true}]},{"id":100216,"name":"Zambia","rows":[{"id":14435,"name":"1.A.3  Transport","unitId":17,"cells":[{"column":36,"numberValue":1220.45460000000000},{"column":42,"numberValue":584.63000000000000}],"excludeFromChart":true}]},{"id":100217,"name":"Zimbabwe","rows":[{"id":14435,"name":"1.A.3  Transport","unitId":17,"cells":[{"column":36,"numberValue":2045.58000000000000},{"column":42,"numberValue":1071.00000000000000},{"column":48,"numberValue":1302.63700000000000}],"excludeFromChart":true}]}],"generated":"Saturday, 5 February 2022 01:30:15 CET"}